Workbook

Sheet Leggimi
A1: Impianto birrificio: elenco completo, costi e business plan
A2: ="Vendite a regime: "&Parametri!C19&" fusti e "&Parametri!C20&" bottiglie all'anno ("&ROUND(Parametri!C26*100,0)&"% del volume in fusti). Preparato il 06/10/2026, aggiornato il 07/10/2026 (mutuo, 15 anni, clienti, vendite in n. di fusti e bottiglie)." -> Vendite a regime: 144 fusti e 3300 bottiglie all'anno (80% del volume in fusti). Preparato il 06/10/2026, aggiornato il 07/10/2026 (mutuo, 15 anni, clienti, vendite in n. di fusti e bottiglie).
A4: Cosa contiene
A5: Riepilogo | B5: Impianto scelto: investimento, capacità, ricavi, utile, payback, punto di pareggio.
A6: Mercato | B6: Dati Assobirra 2025, prezzi di riferimento, SWOT.
A7: Normativa e fisco | B7: Autorizzazioni (SUAP, ASL, ADM), accise, regime fiscale.
A8: Parametri | B8: Tutte le ipotesi (modificabili, celle blu), compresi i dati del mutuo (sezione 8).
A9: Impianto e costi | B9: Elenco completo di macchinari, locale e avvio, con costo di ogni voce (impianto scelto).
A10: Materie prime | B10: Ricette tipo, consumi e costo per ettolitro e per cotta.
A11: Business plan | B11: Business plan a 15 anni dell'impianto scelto, senza mutuo (righe 4–58) e con mutuo (righe 60–79).
A12: Cadenza produzione | B12: Rotazione dei 3 fermentatori con una cotta a settimana e carico di lavoro.
A13: Break-even | B13: Litri da vendere per il pareggio e per rientrare in 5 anni.
A14: Cronoprogramma | B14: Tempi indicativi di avvio.
A15: Checklist locale | B15: Punti da verificare nel sopralluogo e voci di costo collegate.
A16: Fonti | B16: Link alle fonti usate.
A17: Clienti potenziali | B17: Pub, bar, ristoranti, agriturismi e altri locali nel raggio di 30 km, con priorità, stima di fusti e stato dei contatti; elenco dei birrifici concorrenti.
A19: Convenzioni
A20: Blu | B20: Ipotesi o dati inseriti da modificare.
A21: Nero | B21: Formule.
A22: Verde | B22: Collegamenti ad altri fogli.
A24: Situazione dichiarata (06/10/2026)
A25: Locale | B25: Di proprietà (affitto 0), 40–80 m², stato da verificare; il socio è architetto.
A26: Soci e fisco | B26: Due soci non familiari, SRL (forfettario escluso), entrambi con un altro lavoro.
A27: Compensi | B27: Nessun compenso ai soci: gli utili restano nella società e il tempo di lavoro non viene valorizzato.
A28: Obiettivo | B28: Secondo lavoro che si autofinanzia; 20–30 ore a settimana in due. Il budget iniziale era 30.000 €, ma l'impianto scelto lo supera (vedi Riepilogo, investimento totale): per questo è previsto un mutuo.
A29: Vendite | B29: Fusti per eventi e feste (oggi da 2–5 al mese, obiettivo dichiarato 8–10). Il modello a regime assume i fusti e le bottiglie all'anno indicati in Parametri (oggi ≈ 17 fusti da 30 L al mese): è molto di più, da verificare con preordini ed eventi. Bottiglie a pub e bar; attrezzatura usata valutata caso per caso.
A31: Avvertenze
A32: 1 | B32: Molti costi sono stime mie (colonna Tipo = S): vanno sostituiti con preventivi reali.
A33: 2 | B33: I fermentatori UT-200 PRO sono su ordinazione: chiedere a BrewTaurus conferma di prezzo, tempi e documenti PED. Mulino, trasporto e molte voci di contorno non sono verificati.
A34: 3 | B34: Le informazioni su normativa e fisco sono sintesi di fonti pubbliche: verificare con commercialista, SUAP, ASL e ADM.
A35: 4 | B35: I risultati dipendono molto dai volumi di vendita: il modello non garantisce che i clienti ci siano.
A36: 5 | B36: Il tasso del mutuo (Parametri riga 102) è un'ipotesi mia: per piccoli importi i dati 2026 indicano tassi più alti. Sostituirlo con preventivi di banca o Confidi. Istruttoria, imposta sostitutiva e spese di gestione del mutuo non sono incluse.

Sheet Riepilogo
A1: Riepilogo: impianto completo e business plan
A2: Impianto scelto: K220 2V + 3 UT-200 con i fusti e le bottiglie all'anno dei Parametri. Tutto collegato ai fogli di dettaglio.
A4: Indicatore | B4: K220 2V + 3×UT-200 | C4: Commento
A5: Investimento totale (con imprevisti e circolante) | B5: ='Impianto e costi'!G73 -> 60311.691 | C5: Comprende macchinari, locale, avvio e capitale circolante
A6: di cui macchinari e impianti (A–E) | B6: ='Impianto e costi'!G17+'Impianto e costi'!G26+'Impianto e costi'!G34+'Impianto e costi'!G41+'Impianto e costi'!G54 -> 53123
A7: di cui avvio e autorizzazioni (F) | B7: ='Impianto e costi'!G66 -> 4300
A8: Capacità produttiva (hl/anno) | B8: =Parametri!C17 -> 82.8 | C8: Limitata dai fermentatori, non dalla sala cottura
A9: Ricavi anno 3 | B9: ='Business plan'!E17 -> 20298
A10: Ricavi a regime (anno 5) | B10: ='Business plan'!G17 -> 23880
A11: EBITDA a regime (margine operativo) | B11: ='Business plan'!G43 -> 11126.763 | C11: Ricavi − costi variabili − costi fissi. Se negativo, i costi fissi superano il margine delle vendite
A12: Utile netto a regime | B12: ='Business plan'!G47 -> 4051.4601
A13: Ore di lavoro a settimana in due (stima, non valorizzate) | B13: ='Business plan'!G49/Parametri!$C$12 -> 9.7444746 | C13: Voi avete 20–30 ore a settimana disponibili
A14: Payback senza mutuo (anni) | B14: ='Business plan'!B56 -> 7.8678594 | C14: 'oltre 15 anni' = l'investimento non rientra nel periodo
A15: EBITDA a regime senza affitto | B15: ='Business plan'!G43+Parametri!$C$73*12 -> 11126.763 | C15: Come la riga 11 se l'affitto è 0 (locale di proprietà)
A16: Payback semplice (anni) – approssimato, senza affitto | B16: =IF(B15>0,B5/B15,"non rientra") -> 5.4204164 | C16: Investimento ÷ EBITDA; ignora imposte e ramp-up
A17: Litri da vendere per il pareggio operativo | B17: ='Break-even'!C12 -> 1837.6587
A18: …in percentuale della capacità vendibile | B18: ='Break-even'!C14 -> 0.23118693 | C18: Oltre 100% = pareggio oltre la capacità
A19: Litri da vendere per rientrare in 5 anni | B19: ='Break-even'!C16 -> 5709.2901
A20: …in percentuale della capacità vendibile | B20: ='Break-even'!C17 -> 0.71825812
A21: Volume venduto a regime (hl/anno) | B21: ='Business plan'!G8/100 -> 54.09 | C21: ="Fusti + bottiglie dei Parametri. Utilizzo della capacità: "&ROUND(Parametri!C32*100,0)&"% (controllo: "&Parametri!C33&")" -> Fusti + bottiglie dei Parametri. Utilizzo della capacità: 68% (controllo: OK)
A22: EBITDA a regime se l'INPS fosse dovuta (2 persone, contributo minimo) | B22: ='Business plan'!G43+'Business plan'!G35-2*(Parametri!$C$79*Parametri!$C$78+Parametri!$C$81) -> 2084.0434 | C22: Da verificare con il commercialista: con un altro lavoro l'obbligo può non scattare
A23: ="Fusti da "&Parametri!C21&" L al mese necessari per il pareggio (stesso mix fusti/bottiglie)" -> Fusti da 30 L al mese necessari per il pareggio (stesso mix fusti/bottiglie) | B23: =IF(ISNUMBER('Break-even'!C12),'Break-even'!C12*Parametri!$C$26/Parametri!$C$21/12,"n/d") -> 4.0768911 | C23: Da confrontare con i fusti/mese previsti nei Parametri
A24: Come leggere i risultati
A25: ="• Un solo impianto: K220 2V (brewhouse da 220 L, batch "&Parametri!C7&" L) con "&Parametri!C8&" UT-200 PRO a rotazione, acqua calda separata per lo sparge e CIP kit manuale. Una cotta a settimana a regime: ≈ "&ROUND(Parametri!C15,0)&" cotte e ≈ "&ROUND(Parametri!C17,0)&" hl di produzione all'anno (vedi foglio Cadenza produzione)." -> • Un solo impianto: K220 2V (brewhouse da 220 L, batch 180 L) con 3 UT-200 PRO a rotazione, acqua calda separata per lo sparge e CIP kit manuale. Una cotta a settimana a regime: ≈ 46 cotte e ≈ 83 hl di produzione all'anno (vedi foglio Cadenza produzione).
A26: ="• Nei primi anni si vende meno ("&ROUND(Parametri!C39*100,0)&"%, "&ROUND(Parametri!C40*100,0)&"%, "&ROUND(Parametri!C41*100,0)&"% del volume a regime) e la cotta non è settimanale; dal quarto anno si va a regime con circa "&ROUND(Parametri!C22,0)&" fusti da "&Parametri!C21&" L al mese ("&ROUND(Parametri!C22*Parametri!C21,-1)&" L): obiettivo da verificare con preordini ed eventi prima di investire." -> • Nei primi anni si vende meno (40%, 65%, 85% del volume a regime) e la cotta non è settimanale; dal quarto anno si va a regime con circa 12 fusti da 30 L al mese (360 L): obiettivo da verificare con preordini ed eventi prima di investire.
A27: ="• Il locale è da verificare (Checklist locale) e la quota lavori in Parametri cambia l'investimento. "&IF(Parametri!C77=0,"L'INPS è a 0 perché entrambi avete un altro lavoro: va verificata (la riga 22 mostra cosa succede se è dovuta).","L'INPS è calcolata per "&Parametri!C77&" persone (Parametri riga 66): verificare con commercialista/INPS se è davvero dovuta.") -> • Il locale è da verificare (Checklist locale) e la quota lavori in Parametri cambia l'investimento. L'INPS è a 0 perché entrambi avete un altro lavoro: va verificata (la riga 22 mostra cosa succede se è dovuta).
A28: • Prezzi dei macchinari letti sul sito BrewTaurus; molte voci di contorno sono stime mie (colonna Tipo = S). Una soluzione PRO (brewhouse BH-150/BH-400) richiede preventivo: i prezzi non sono pubblici.
A29: • Il mutuo (Parametri, sezione 8) è inserito nel Business plan dalla riga 60. Le righe 5–23 qui sopra mostrano l'attività senza mutuo; le righe 32–41 mostrano la situazione con il mutuo.
A31: Con mutuo (Parametri, sezione 8)
A32: Importo del mutuo | B32: =Parametri!C101 -> 60311.691 | C32: Quota finanziata e importo si impostano in Parametri righe 88–89
A33: Capitale proprio da versare | B33: ='Impianto e costi'!G73-Parametri!C101 -> 0 | C33: Investimento totale − mutuo
A34: Rata annua dopo il preammortamento | B34: =Parametri!C106 -> 8403.2385 | C34: Durata e tasso in Parametri righe 91–93
A35: Interessi totali pagati sul mutuo | B35: ='Business plan'!B78 -> 27942.512 | C35: Costo del finanziamento su tutta la durata
A36: Copertura del debito minima | B36: =IF(COUNT('Business plan'!C72:Q72)=0,"n/d",MIN('Business plan'!C72:Q72)) -> 0.24053449 | C36: Sotto 1,0x la gestione non basta a pagare le rate e i soci devono versare cassa. Le banche guardano di solito valori ben sopra 1 (indicativo)
A37: Flusso di cassa dopo le rate – anno 1 | B37: ='Business plan'!C71 -> -3206.3254 | C37: Negativo = fabbisogno di cassa dei soci
A38: Flusso di cassa dopo le rate – anno 3 | B38: ='Business plan'!E71 -> 75.142451
A39: Flusso di cassa dopo le rate – anno 5 | B39: ='Business plan'!G71 -> 1894.7691 | C39: Dipende dalla durata del mutuo (Parametri riga 103): se è già finito, la rata non c'è più
A40: Esborso massimo cumulato dei soci (picco) | B40: ='Business plan'!B77 -> 6381.0416 | C40: Capitale proprio più eventuali versamenti negli anni deboli
A41: Payback dei soci (anni per recuperare capitale proprio e versamenti) | B41: ='Business plan'!B76 -> 6.393386 | C41: Se il mutuo copre tutto, il capitale proprio è 0 e conta l'esborso di cassa nei primi anni

Sheet Mercato
A1: Analisi di mercato – birra artigianale in Italia
A2: Dati da Assobirra Annual Report 2025, Unionbirrai e fonti di settore citate in Fonti. Prezzi: indicativi.
A4: Indicatore | B4: Valore | C4: Unità | D4: Fonte / nota
A5: Consumi di birra in Italia 2025 | B5: 21.2 | C5: milioni hl | D5: Assobirra Annual Report 2025 (−2,5% sul 2024)
A6: Produzione di birra in Italia 2025 | B6: 16.8 | C6: milioni hl | D6: Assobirra (−2,5% sul 2024)
A7: Consumo pro capite 2024 | B7: 36.4 | C7: L/anno | D7: Assobirra Annual Report 2024
A8: Birrifici artigianali attivi 2025 | B8: 1008 | C8: n | D8: Assobirra: 1.008 (1.007 nel 2024)
A9: Produzione artigianale 2025 | B9: 470000 | C9: hl | D9: Assobirra (480.000 nel 2024)
A10: Quota di mercato artigianale (volume) 2025 | B10: 0.022 | C10: % | D10: Assobirra (2,3% nel 2024); oltre il 20% in valore (businessonline.it)
A11: Segmento analcolico/low-alcol 2025 | B11: 0.0389 | C11: % | D11: Assobirra: quota raddoppiata da 2,1% a 3,9%
A12: Addetti nei birrifici artigianali 2025 | B12: 3120 | C12: n | D12: Assobirra / Cronache di Birra
A13: Produzione media per birrificio artigianale | B13: =B9/B8 -> 466.26984 | C13: hl/anno | D13: Calcolato: 470.000 hl ÷ 1.008. La mediana è molto più bassa: la maggior parte dei birrifici produce poche centinaia di hl.
A15: Prezzi di riferimento | B15: Min | C15: Max | D15: Fonte / nota
A16: Fusto 20–30 L all'ingrosso Horeca (€/L) | B16: 3 | C16: 5 | D16: ilmiobusinessplan.com; softwarebusinessplan.it
A17: Birra alla spina nel locale (€/L) | B17: 6 | C17: 12 | D17: ilmiobusinessplan.com
A18: Bottiglia artigianale in negozio specializzato, 33 cl (€) | B18: 4 | C18: 6 | D18: La Casetta Craft Beer Crew
A19: Prezzo medio al litro canale Horeca (€/L) | B19: 10 | C19: 10 | D19: La Casetta Craft Beer Crew (retail ≈3 €/L)
A20: Fusto 20 L venduto online al consumatore, IVA inclusa (€) | B20: 89 | C20: 160 | D20: Birra Cocca Mia, Birra Flea 89 €; Birrificio Caligola 160 € (saporitipicipiemontesi.it)
A22: Lettura del mercato
A23: • Mercato maturo e in leggero calo: consumi totali −2,5% nel 2025. La birra artigianale tiene (quota stabile ≈2,2% a volume ma oltre il 20% a valore), ma non cresce.
A24: • Offerta affollata: oltre 1.000 birrifici artigianali per 470.000 hl. In media meno di 500 hl a birrificio: un impianto da pochi ettolitri/anno è una nicchia, spesso integrata in un'altra attività.
A25: • Margine: il prezzo al litro artigianale (3–5 €/L ingrosso, 6–12 €/L alla spina) è molto sopra l'industriale (circa 3 €/L al retail), ma richiede brand, qualità costante e vendita diretta.
A26: • Segmenti in crescita: analcolico/low-alcol (≈3,9% del mercato) e prodotti locali/di territorio. Un'offerta di birre leggere e bevibili è coerente con la domanda.
A27: ="• Canali: pub, ristoranti, enoteche, beer shop, mercati, eventi, vendita diretta e taproom. Il fusto è il canale principale ("&ROUND(Parametri!C26*100,0)&"% del volume nel modello) ma ha il prezzo più basso." -> • Canali: pub, ristoranti, enoteche, beer shop, mercati, eventi, vendita diretta e taproom. Il fusto è il canale principale (80% del volume nel modello) ma ha il prezzo più basso.
A28: • Rischi: prezzo (concorrenza di marchi industriali e altri artigianali), costi di energia e materie prime, stagionalità, logistica e crediti verso i locali.
A29: • Prima di investire: mappare i locali e i concorrenti entro 50–80 km, fare assaggi e preordini, e chiedere ai primi 5–10 clienti volumi e prezzi reali.
A31: SWOT sintetica
A32: Punti di forza | B32: Debolezze | C32: Opportunità | D32: Minacce
A33: Impianto moderno BrewTaurus (acciaio, glicole, pressione); costi iniziali contenuti rispetto a un impianto da 10 hl | B33: Capacità limitata (circa 80 hl/anno con 3 fermentatori); investimento elevato rispetto ai ricavi: il rientro dipende dai volumi venduti | C33: Birre leggere/NoLo, prodotti di territorio, vendita diretta e taproom | D33: Mercato maturo e stagnante; concorrenza di oltre 1.000 birrifici
A34: Controllo totale su ricette e qualità; possibilità di scalare con altri tank | B34: Poco tempo disponibile: entrambi avete un altro lavoro; dipendenza da voi due | C34: Fidelizzazione di ristoranti e locali con rotazione fusti | D34: Aumento dei costi di energia e materie prime
A35: Accisa ridotta per microbirrifici sotto i 10.000 hl | B35: Pre-order e consegne non immediate; documenti PED da verificare per l'uso commerciale | C35: Eventi, collaborazioni con aziende agricole e hotel | D35: Burocrazia e tempi di autorizzazione (ASL, ADM)

Sheet Normativa e fisco
A1: Normativa italiana e fiscalità – adempimenti per aprire un birrificio
A2: Sintesi informativa basata su fonti pubbliche citate in Fonti. Non è consulenza legale/fiscale: verificare con commercialista, SUAP, ASL e ADM.
A4: Adempimento | B4: Ente | C4: Cosa prevede | D4: Tempi indicativi | E4: Costo stimato (€) | F4: Note e verifiche
A5: Partita IVA e codice ATECO | B5: Agenzia delle Entrate | C5: Apertura P.IVA con ATECO 11.05.00 (Produzione di birra); scelta ditta individuale/SRL/SAS | D5: Pochi giorni | E5: 0–300 (+ notaio per SRL) | F5: Prima di ogni altra pratica
A6: Iscrizione al Registro Imprese e INPS | B6: Camera di Commercio / INPS | C6: ComUnica telematica; iscrizione alla gestione artigiani/commercianti | D6: Pochi giorni | E6: ≈100–300 | F6: Contributi INPS minimi a carico del titolare
A7: SCIA di avvio attività | B7: SUAP del Comune | C7: Segnalazione certificata di inizio attività produttiva (e di vendita al dettaglio se prevista) | D7: Immediata dopo la presentazione; verifiche successive | E7: ≈100–500 | F7: Verificare destinazione d'uso e agibilità del locale
A8: Notifica sanitaria / registrazione stabilimento | B8: ASL | C8: Registrazione dello stabilimento alimentare (Reg. CE 852/2004); sopralluogo | D8: 1–3 mesi (La Casetta Craft Beer Crew) | E8: 500–2.000 | F8: Locale con pavimenti/pareti lavabili, scarichi, spogliatoio e servizi igienici
A9: Piano HACCP e tracciabilità | B9: ASL / consulente | C9: Autocontrollo (HACCP) e tracciabilità di materie prime e lotti (Reg. CE 178/2002) | D9: Prima dell'avvio | E9: ≈900 | F9: Registro lotti, pulizie, temperature
A10: Etichettatura | B10: Reg. UE 1169/2011 | C10: Denominazione, volume, titolo alcolometrico, lotto, TMC, indicazione degli allergeni, dati dell'operatore, ecc. | D10: Prima della vendita | E10: Grafica nei costi di avvio | F10: Verificare con un consulente quali indicazioni sono obbligatorie per le bevande alcoliche
A11: Licenza fiscale / deposito fiscale | B11: Agenzia delle Dogane e dei Monopoli (ADM) | C11: Autorizzazione come deposito fiscale/microbirrificio, codice accisa, verifica tecnica degli impianti, registri di carico e scarico, dichiarazioni periodiche | D11: Alcuni mesi | E11: 1.000–2.000 (La Casetta) | F11: La cauzione è calcolata da ADM sulla capacità dei serbatoi e sul prodotto che si intende detenere in sospensione di accisa
A12: Accisa sulla birra | B12: ADM | C12: €2,98 per ettolitro e per grado Plato nel 2026–2027; si paga all'immissione in consumo | D12: Mensile (dichiarazioni) | E12: Calcolata nel modello | F12: Riduzione per microbirrifici ≤10.000 hl: 40% o 50% a seconda della fonte (vedi Parametri); semplificazioni per i piccolissimi
A13: Definizione di birra artigianale | B13: L. 154/2016 (e decreti attuativi) | C13: Piccolo birrificio indipendente, ≤200.000 hl/anno, birra non pastorizzata né microfiltrata | D13: — | E13: — | F13: Rilevante per l'accisa ridotta e per la dicitura 'artigianale'
A14: Antincendio | B14: Vigili del Fuoco | C14: CPI solo se l'attività supera soglie di legge; in ogni caso estintori e valutazione dei rischi | D14: Dipende | E14: ≈600 (stima) | F14: Chiedere al tecnico
A15: Sicurezza sul lavoro | B15: Normativa D.Lgs. 81/2008 | C15: Valutazione rischi, formazione, eventuale RSPP se ci sono dipendenti | D15: Prima dell'avvio | E15: Da preventivare | F15: Valido anche per chi lavora in famiglia/ditta
... A18: Trasporto di prodotti sottoposti ad accisa | B18: ADM | C18: Documenti di accompagnamento per merce sotto accisa o in sospensione | D18: Per spedizione | E18: — | F18: Chiedere al commercialista/ADM
A20: Imposte e regime fiscale
A21: Voce | B21: Regime | C21: Aliquota/regola | F21: Note
A22: IVA | B22: Tutti | C22: 22% sulla vendita di birra (aliquota ordinaria) | F22: Acquisti con IVA detraibile solo in regime ordinario
A23: Imposta sostitutiva | B23: Forfettario (ditta individuale) | C23: 15% (5% per i primi 5 anni se requisiti); base imponibile = ricavi × coefficiente 40% − contributi INPS | F23: Limite ricavi 85.000 € (verificare); l'IVA sugli acquisti non è detraibile; niente IRAP
A24: IRES | B24: SRL | C24: 24% sull'utile | F24: Più oneri amministrativi (bilancio, notaio)
A25: IRAP | B25: SRL | C25: 3,9% base (varia per regione) | F25: Nel modello è applicata sull'EBIT come semplificazione
A26: Accisa | B26: Tutti | C26: 2,98 €/hl/°P, con riduzione per microbirrifici | F26: Vedi Parametri per la riduzione usata
A27: INPS 2026 | B27: Artigiani (titolare e coadiuvanti) | C27: Minimale 18.808 €; contributo fisso 4.521,36 € a persona; 24% sul reddito oltre il minimale fino a 56.224 €; riduzione 35% per i forfettari su richiesta | F27: Circolare INPS 14/2026. Nel modello l'INPS è calcolato per ciascuna persona
A28: Due persone: familiari | B28: Ditta individuale + impresa familiare | C28: Se il secondo è un familiare (coniuge, parenti/affini entro i gradi di legge) può essere coadiuvante: il forfettario resta applicabile, l'imposta sostitutiva è dovuta dal titolare sull'intero reddito, il coadiuvante versa i propri contributi INPS | F28: Limite di 20.000 € di spese per lavoro nel forfettario (pmi.it). Verificare con commercialista
A29: Due persone: non familiari | B29: SNC / SAS / SRL | C29: Il forfettario non è applicabile alle società: IRPEF sui soci (snc/sas) oppure IRES+IRAP (SRL); i soci che lavorano versano l'INPS | F29: Scelta: SRL, quindi nel modello regime 2 (IRES + IRAP)
A30: SRL: adempimenti | B30: Notaio / Registro Imprese | C30: Atto costitutivo notarile, deposito annuale del bilancio, diritto annuale alla Camera di Commercio, capitale sociale minimo (verificare importo) | F30: Gli amministratori compensati versano alla gestione separata INPS; chiarire con il commercialista. Con un altro lavoro l'obbligo INPS artigiani può non scattare
A32: Agevolazioni e finanziamenti (controllati a ottobre 2026: da confermare con commercialista ed enti)
A33: • Autoimpiego Centro-Nord (Invitalia, under 35, fondo perduto): richiede disoccupazione/inattività o condizioni simili. Con un altro lavoro probabilmente non spetta: verificare.
A34: • Piemonte, Finpiemonte (L.R. 32/23 Autoimpiego): 70% a tasso zero e 30% a tasso bancario per macchinari e impianti; i requisiti sulla condizione lavorativa dei soci vanno verificati.
A35: • Nuova Sabatini: contributo sugli interessi, solo beni nuovi, finanziamenti da 20.000 €, durata massima 5 anni.
A36: • Fondo di Garanzia PMI: garanzia fino all'80% sui finanziamenti per investimenti, gratuita per le microimprese, richiesta tramite banca o Confidi.
A37: • Bandi camerali e credito d'imposta o ammortamenti agevolati per beni strumentali: solo con commercialista, in base al regime.

Sheet Parametri
A1: Parametri e ipotesi del modello
A2: Blu = ipotesi modificabili; nero = formule; verde = collegamenti ad altri fogli. Tutti i prezzi sono IVA esclusa e in euro reali (senza inflazione).
A4: Parametro | B4: Unità | C4: Valore | D4: Fonte / nota
A5: 1. Scenari impianto (capacità produttiva)
A6: Nome scenario | C6: K220 2V + 3×UT-200 | D6: Impianto scelto: una cotta a settimana nel K220 2V (acqua calda separata, CIP kit manuale), 3 fermentatori UT-200 PRO (PED) a rotazione
A7: Volume di una cotta (netto nel fermentatore) | B7: L | C7: 180 | D7: K220 2V: 150–190 L (scelgo 180). I UT-200 hanno 200 L effettivi
A8: Numero fermentatori | B8: n | C8: 3 | D8: Una cotta a settimana, ~2 settimane di fermentazione + maturazione/pulizia: servono 3 tank a rotazione
A9: Occupazione del tank per ciclo (fermentazione + maturazione + pulizia) | B9: giorni | C9: 21 | D9: 2 settimane di fermentazione + circa 1 settimana tra raffreddamento, confezionamento e CIP. Per le lager serve di più
A10: Utilizzo massimo dei tank nell'anno | B10: % | C10: 0.9 | D10: Stima mia: fermate, pulizie, ritardi
A11: Cotte a settimana (massimo) | B11: n | C11: 1 | D11: Una cotta a settimana (di solito nel weekend)
A12: Settimane di produzione all'anno | B12: sett. | C12: 46 | D12: Esclude ferie e fermate
A13: Cotte/anno consentite dai tank | B13: n | C13: =C8*365*C10/C9 -> 46.928571 | D13: Calcolo: n. tank × 365 × utilizzo ÷ giorni per ciclo
A14: Cotte/anno consentite dalla sala cottura | B14: n | C14: =C11*C12 -> 46
A15: Cotte/anno (minimo dei due limiti) | B15: n | C15: =ROUND(MIN(C13,C14),0) -> 46
A16: Capacità produttiva annua | B16: L | C16: =C15*C7 -> 8280
A17: Capacità produttiva annua | B17: hl | C17: =C16/100 -> 82.8
A18: 2. Vendite
A19: Fusti venduti all'anno (a regime) | B19: fusti/anno | C19: 144 | D19: Scelta vostra: al posto del mix 80/20. 200 fusti da 30 L = circa 17 al mese. L'obiettivo dichiarato oggi è 8–10 al mese (≈ 100–120 all'anno): da verificare con preordini ed eventi prima di investire. Nei primi anni si vende meno (percentuali sotto)
A20: Bottiglie vendute all'anno (a regime) | B20: bottiglie/anno | C20: 3300 | D20: Scelta vostra: al posto del mix 80/20. 4.550 bottiglie da 33 cl = circa 1.500 L, un quinto del volume. Il totale (fusti + bottiglie) non può superare la capacità dell'impianto: vedi il controllo più sotto
A21: Capacità del fusto | B21: L | C21: 30 | D21: Fusti inox da 30 L (scelta vostra)
A22: ="Fusti da "&C21&" L venduti al mese (media a regime)" -> Fusti da 30 L venduti al mese (media a regime) | B22: n/mese | C22: =C19/12 -> 12 | D22: Calcolato: fusti all'anno ÷ 12
A23: Volume venduto in fusti a regime | B23: L/anno | C23: =C19*C21 -> 4320 | D23: Fusti all'anno × capacità del fusto
A24: Volume venduto in bottiglia a regime | B24: L/anno | C24: =C20*C38 -> 1089 | D24: Bottiglie all'anno × volume della bottiglia
A25: Volume venduto a regime (domanda) | B25: L/anno | C25: =C23+C24 -> 5409 | D25: Fusti + bottiglie, in litri
A26: Quota volume venduta in fusti | B26: % | C26: =IF(C25=0,0,C23/C25) -> 0.79866889 | D26: Calcolata dai volumi sopra (non è più un'ipotesi: serve per costi e ricavi)
A27: Quota volume venduta in bottiglia | B27: % | C27: =1-C26 -> 0.20133111 | D27: Calcolata
A28: Perdite di processo e campioni | B28: % | C28: 0.04 | D28: Stima mia: trub, linee, campionature, invenduto
A29: Capacità venduta all'anno (a regime) | B29: L/anno | C29: =C16*(1-C28) -> 7948.8 | D29: ="Capacità produttiva di tank e sala cottura (riga 16: "&C8&" fermentatori, "&C9&" giorni per ciclo tra fermentazione, maturazione e pulizia, "&ROUND(C10*100,0)&"% di utilizzo) meno le perdite di processo" -> Capacità produttiva di tank e sala cottura (riga 16: 3 fermentatori, 21 giorni per ciclo tra fermentazione, maturazione e pulizia, 90% di utilizzo) meno le perdite di processo
A30: Capacità massima al mese (media a regime) | B30: L/mese | C30: =C29/12 -> 662.4 | D30: ="Circa "&ROUND(C30/C21,0)&" fusti da "&C21&" L al mese se tutto fosse in fusti. Nel singolo mese dipende da quante cotte cadono (3–5)" -> Circa 22 fusti da 30 L al mese se tutto fosse in fusti. Nel singolo mese dipende da quante cotte cadono (3–5)
A31: Domanda al mese (media a regime) | B31: L/mese | C31: =C25/12 -> 450.75 | D31: Fusti e bottiglie indicati sopra, divisi per 12
A32: Utilizzo della capacità a regime | B32: % | C32: =IF(C29=0,0,C25/C29) -> 0.68048007 | D32: Oltre 100% = la domanda supera quello che l'impianto può produrre
A33: Controllo capacità | C33: =IF(C25<=C29,"OK","SUPERATA") -> OK | D33: =IF(C25<=C29,"La domanda a regime rientra nella capacità: margine di "&ROUND(C29-C25,0)&" L all'anno","Domanda oltre la capacità: il modello vende solo "&ROUND(C29,0)&" L all'anno invece di "&ROUND(C25,0)&". Riducete fusti o bottiglie, oppure aggiungete fermentatori o cotte") -> La domanda a regime rientra nella capacità: margine di 2540 L all'anno
A34: Fusti massimi all'anno con le bottiglie indicate | B34: fusti/anno | C34: =MAX(0,(C29-C24)/C21) -> 228.66 | D34: Quanti fusti entrano nella capacità, lasciando alle bottiglie il volume indicato
A35: Bottiglie massime all'anno con i fusti indicati | B35: bottiglie/anno | C35: =MAX(0,(C29-C23)/C38) -> 10996.364 | D35: Quante bottiglie entrano nella capacità, lasciando ai fusti il volume indicato
A36: Prezzo fusti (IVA esclusa, accisa inclusa) | B36: €/L | C36: 4 | D36: Fusti per eventi e feste a privati: 89–160 € IVA inclusa per 20 L (birrifici online) ≈ 3,65–6,5 €/L senza IVA. Uso 4,00 (≈ 98 € per un fusto da 20 L, ≈ 146 € da 30 L, IVA inclusa). Pub: 3–5 €/L
A37: Prezzo bottiglia 33 cl (IVA esclusa, accisa inclusa) | B37: €/bottiglia | C37: 2 | D37: Stima mia: in negozio specializzato 4–6 € a 33 cl (La Casetta Craft Beer Crew); all'ingrosso circa 2–3 €
A38: Volume della bottiglia | B38: L | C38: 0.33 | D38: Bottiglia da 33 cl
A39: Domanda raggiunta – anno 1 (% del volume a regime) | B39: % | C39: 0.4 | D39: Stima mia: i primi anni si vende meno
A40: Domanda raggiunta – anno 2 | B40: % | C40: 0.65
A41: Domanda raggiunta – anno 3 | B41: % | C41: 0.85
A42: Domanda raggiunta – anno 4 | B42: % | C42: 1 | D42: Da qui una cotta a settimana
A43: Domanda raggiunta – anno 5 e successivi | B43: % | C43: 1 | D43: Gli anni 6–15 restano uguali all'anno 5
A44: 3. Costi variabili unitari
A45: Materie prime (malto, luppolo, lievito, additivi) – media pesata | B45: €/hl | C45: ='Materie prime'!L9 -> 50.4 | D45: Calcolato nel foglio Materie prime
A46: Detergenti e sanitizzanti | B46: €/hl | C46: 4 | D46: Stima mia: caustico, acido, sanitizzante
A47: Grado Plato medio ponderato | B47: °P | C47: ='Materie prime'!C9 -> 13.7 | D47: Serve per l'accisa
A48: Energia elettrica per ettolitro prodotto | B48: kWh/hl | C48: 50 | D48: Stima mia: riscaldamento acqua/mosto (~35–40), pompe, glicole; da misurare
A49: Prezzo energia elettrica | B49: €/kWh | C49: 0.25 | D49: Stima mia per utenza business; verificare il contratto
A50: Acqua per ettolitro di birra | B50: m³/hl | C50: 0.6 | D50: Stima mia (≈6 L per litro: lavaggi inclusi)
A51: Costo acqua + fognatura | B51: €/m³ | C51: 3 | D51: Stima mia: varia molto per gestore
A52: Bottiglia vuota 33 cl | B52: € | C52: 0.22 | D52: Stima mia: da verificare con i fornitori di vetro
A53: Tappo corona | B53: € | C53: 0.02 | D53: Fonte: fermentobirra.com (0,02 €)
A54: Etichetta | B54: € | C54: 0.05 | D54: Fonte: fermentobirra.com (0,04 €), arrotondato
A55: Scatola/cartone per bottiglia | B55: € | C55: 0.04 | D55: Fonte: fermentobirra.com (0,40 € per scatola da 12), ≈0,03–0,04 €/bottiglia
A56: Contributo ambientale CONAI per bottiglia | B56: € | C56: 0.005 | D56: Stima mia: da verificare con CONAI
A57: Consumabili fusti (CO2, guarnizioni) | B57: €/hl | C57: 3 | D57: Stima mia
A58: Logistica e consegne | B58: % ricavi | C58: 0.025 | D58: Stima mia: carburante, corrieri. Se consegnate voi i fusti il costo non sparisce (carburante, usura del mezzo): potrebbe scendere verso il 2%
A59: ="Fusto inox "&C21&" L (acquisto)" -> Fusto inox 30 L (acquisto) | B59: € | C59: 110 | D59: Stima mia: da verificare con i fornitori. Il fusto PET monouso costa meno ma non è riutilizzabile
A60: Giri annui di un fusto (rotazione) | B60: n | C60: 7 | D60: Stima mia: gli eventi durano da 1 giorno a 1 settimana, quindi i fusti tornano presto; i picchi stagionali richiedono comunque margine
A61: 4. Fisco e accise
A62: Aliquota accisa ordinaria 2026–2027 | B62: €/hl/°P | C62: 2.98 | D62: Legge di Bilancio 2026 (da 2,99 a 2,98 per il 2026–27). Fonte: beverfood.com, economymagazine.it
A63: Riduzione per microbirrifici (≤10.000 hl/anno) | B63: % | C63: 0.4 | D63: Fonti discordanti: 40% (La Casetta Craft Beer Crew 2026, DM 2019) o 50% (fiscodiprossimita.it, LdB 2025). Uso 40% (prudente). Confermare con ADM
A64: Regime fiscale (1 = forfettario ditta individuale; 2 = SRL/società ordinaria) | B64: 1/2 | C64: 2 | D64: Siete 2 soci non familiari e avete scelto la SRL: forfettario non applicabile, quindi 2 = IRES + IRAP
A65: Coefficiente di redditività ATECO 11.05.00 (forfettario) | B65: % | C65: 0.4 | D65: Fonte: partitaiva.it (dato datato)
A66: Aliquota imposta sostitutiva forfettario | B66: % | C66: 0.15 | D66: 15% ordinaria; 5% possibile per i primi 5 anni se requisiti soddisfatti (da verificare)
A67: Limite ricavi forfettario | B67: € | C67: 85000 | D67: Verificare il limite in vigore
A68: IRES (SRL) | B68: % | C68: 0.24 | D68: Aliquota ordinaria
A69: IRAP (SRL) | B69: % | C69: 0.039 | D69: Aliquota base; varia per regione. Semplificazione: calcolata sull'EBIT
A70: Ammortamento impianti e avvio | B70: anni | C70: 10 | D70: Stima mia
A71: Ammortamento fusti | B71: anni | C71: 6 | D71: Stima mia
A72: 5. Costi fissi annui
A73: Affitto locale | B73: €/mese | C73: 0 | D73: Il locale è di vostra proprietà (40–80 m²): affitto 0
A74: Utenze fisse (potenza impegnata, internet, ecc.) | B74: €/mese | C74: 120 | D74: Stima mia
A75: Assicurazioni (RC prodotto, incendio) | B75: €/anno | C75: 1500 | D75: Stima mia
A76: Commercialista, bilancio SRL e consulenze | B76: €/anno | C76: 500 | D76: Valore scelto da voi. La mia stima di partenza era 1.500–2.000 € per una SRL con bilancio: non ho trovato tariffe verificate, chiedere 2–3 preventivi
A77: Persone che versano contributi INPS artigiani | B77: n | C77: 0 | D77: Default 0 perché entrambi avete un altro lavoro: l'obbligo può non scattare (dipende dalla prevalenza e dal tipo di compenso nella SRL). Chiedere a commercialista/INPS; mettere 2 se è dovuto. Con 0 il costo INPS è azzerato
A78: Reddito minimale INPS artigiani 2026 | B78: € | C78: 18808 | D78: Circolare INPS n. 14/2026 (ecnews.it, soluzionetasse.com)
A79: Aliquota contributiva IVS artigiani | B79: % | C79: 0.24 | D79: 24% (commercianti 24,48%). Oltre il limite della prima fascia l'aliquota sale di 1 punto: non modellato
A80: Limite di reddito della prima fascia | B80: € | C80: 56224 | D80: Circolare INPS n. 14/2026
A81: Contributo maternità annuo per persona | B81: € | C81: 7.44 | D81: 0,62 €/mese
A82: Riduzione contributi forfettari (se richiesta) | B82: % | C82: 0 | D82: Il forfettario può chiedere la riduzione del 35% entro il 28 febbraio (fiscal-focus.it). Default 0 = non richiesta. Verificare col commercialista
A83: Fideiussione/cauzione ADM (costo annuo) | B83: €/anno | C83: 500 | D83: Stima mia: la cauzione è calcolata da ADM sulla capacità dei serbatoi
A84: Marketing e commerciale | B84: €/anno | C84: 0 | D84: Azzerato: vendita a eventi e passaparola (voi pensate di poterlo ridurre davvero). Le campionature sono nella voce di lancio
... A89: Mesi di affitto come cauzione | B89: mesi | C89: 0 | D89: Stima mia
A90: 6. Ore di lavoro (solo per il carico di lavoro, non valorizzate)
A91: Ore di lavoro per cotta (cotta, pulizie, travasi) | B91: ore | C91: 10 | D91: Stima mia
A92: Ore per ettolitro venduto (confezionamento, consegne, vendite) | B92: ore/hl | C92: 2.5 | D92: Stima mia
A93: 7. Investimento
A94: Capitale circolante iniziale | B94: mesi di costi | C94: 2 | D94: Mesi di costi (variabili + fissi) dell'anno 1
A95: Imprevisti sull'investimento | B95: % | C95: 0.1 | D95: Stima prudenziale sulle voci A–F
A96: Sconto medio acquistando usato | B96: % | C96: 0.4 | D96: Stima mia: da verificare con annunci reali (mulino, chiller, riempitrice, pompe)
A97: Quota dei lavori di adeguamento del locale necessari | B97: % | C97: 1 | D97: 100% = tutti i lavori elencati nella sezione E; il locale è da verificare (sopralluogo del socio architetto). Con 0% il locale è già pronto
A98: 8. Finanziamento (mutuo)
A99: Quota dell'investimento finanziata con il mutuo | B99: % | C99: =MIN(IF(C100>0,C100/'Impianto e costi'!$G$73, 1)) -> 1 | D99: Se l'importo fisso (riga sotto) è vuoto vale 100% = il mutuo copre tutto l'investimento (macchinari, lavori, avvio, imprevisti e circolante); con un importo fisso si ricalcola da solo. Per non avere mutuo scrivere 0%
A100: Importo fisso del mutuo (facoltativo) | B100: € | D100: Se compilato, sostituisce la percentuale della riga sopra (non può superare l'investimento totale). Lasciare vuoto per usare la percentuale
A101: Importo del mutuo | B101: € | C101: =MIN(IF(C100>0,C100,C99*'Impianto e costi'!$G$73),'Impianto e costi'!$G$73) -> 60311.691 | D101: Calcolato: importo fisso se inserito, altrimenti percentuale × investimento totale
A102: Tasso d'interesse annuo nominale (TAN) | B102: % | C102: 0.07 | D102: Ipotesi mia, da sostituire con preventivi di banca/Confidi. Dati 2026: prestiti alle imprese fino a 50.000 € ≈ 8,8% (Banca d'Italia, 2° trim.); un prestito garantito dal Fondo PMI è offerto a Euribor 3 mesi (≈ 3%) + 5,75%. Il 6% è probabilmente ottimistico
A103: Durata dell'ammortamento (dopo il preammortamento) | B103: anni | C103: 10 | D103: Rate mensili costanti (ammortamento alla francese). Minimo 1 anno
A104: Preammortamento (solo interessi, senza capitale) | B104: anni | C104: 1 | D104: Periodo iniziale in cui si pagano solo gli interessi: aiuta negli anni di avvio, quando le vendite sono ancora basse. 0 = niente preammortamento
A105: Rata mensile dopo il preammortamento | B105: €/mese | C105: =IF(OR(C101<=0,C103<=0),0,-PMT(C102/12,C103*12,C101)) -> 700.26987 | D105: Calcolo: rata costante PMT(tasso/12; mesi; importo)
...

Sheet Cadenza produzione
A1: Cadenza produttiva: una cotta a settimana con 3 fermentatori
A2: Ogni cotta riempie un fermentatore; il tank resta occupato circa 3 settimane (2 di fermentazione + 1 tra raffreddamento, confezionamento e CIP).
A4: Tank | B4: Sett. 1 | C4: Sett. 2 | D4: Sett. 3 | E4: Sett. 4 | F4: Sett. 5 | G4: Sett. 6 | H4: Sett. 7 | I4: Sett. 8 | J4: Sett. 9 | K4: Sett. 10 | L4: Sett. 11 | M4: Sett. 12
A5: Tank 1 | B5: R | C5: F | D5: F | E5: M | F5: R | G5: F | H5: F | I5: M | J5: R | K5: F | L5: F | M5: M
A6: Tank 2 | C6: R | D6: F | E6: F | F6: M | G6: R | H6: F | I6: F | J6: M | K6: R | L6: F | M6: F
A7: Tank 3 | D7: R | E7: F | F7: F | G7: M | H7: R | I7: F | J7: F | K7: M | L7: R | M7: F
A9: Legenda: R = cotta e riempimento (giorno 1); F = fermentazione (circa 14 giorni); M = maturazione, raffreddamento, confezionamento e CIP (circa 1 settimana).
A10: Con 2 settimane di fermentazione un tank è libero dopo circa 3 settimane: servono 3 tank per una cotta a settimana. Con 2 soli tank non c'è margine per pulizie e ritardi.
A12: Carico a regime | B12: Valore | C12: Unità | D12: Come si calcola
A13: Litri per cotta | B13: =Parametri!$C$7 -> 180 | C13: L | D13: Parametri
A14: Cotte all'anno (limite dei tank) | B14: =Parametri!$C$15 -> 46 | C14: n | D14: Dai Parametri: 3 tank × 365 × utilizzo ÷ 21 giorni
A15: Produzione annua a regime | B15: =Parametri!$C$17 -> 82.8 | C15: hl | D15: Capacità produttiva
A16: Venduto a regime (domanda) | B16: =Parametri!$C$25/100 -> 54.09 | C16: hl | D16: Da fusti e bottiglie all'anno indicati
A17: Litri venduti per cotta | B17: =B13*(1-Parametri!$C$28) -> 172.8 | C17: L | D17: Dopo le perdite
A18: ="Fusti da "&Parametri!C21&" L per cotta" -> Fusti da 30 L per cotta | B18: =B17*Parametri!$C$26/Parametri!$C$21 -> 4.6003328 | C18: n | D18: ="Quota fusti: "&ROUND(Parametri!C26*100,0)&"%" -> Quota fusti: 80%
A19: Bottiglie da 33 cl per cotta | B19: =B17*Parametri!$C$27/Parametri!$C$38 -> 105.42429 | C19: n | D19: ="Quota bottiglie: "&ROUND(Parametri!C27*100,0)&"%" -> Quota bottiglie: 20%
A20: Ore di lavoro per cotta (stima) | B20: =Parametri!$C$91+B17/100*Parametri!$C$92 -> 14.32 | C20: ore | D20: Cotta e pulizie + confezionamento, consegne e vendite
A21: Ore a settimana in due (cotta ogni settimana) | B21: =B20 -> 14.32 | C21: ore | D21: Da confrontare con 20–30 ore a settimana disponibili tra voi due

Sheet Impianto e costi
A1: Impianto completo: elenco, specifiche e costi
A2: Impianto scelto: K220 2V + 3×UT-200 PRO. Tipo: V = prezzo letto sul sito BrewTaurus; N = non verificato sul sito; S = stima mia. Prezzi IVA esclusa salvo diversa indicazione.
A4: # | B4: Voce | C4: Dettaglio / specifiche | D4: Tipo | E4: K220 Q.tà | F4: K220 Prezzo | G4: K220 Totale | H4: Note / link
A5: A. Macchinari principali (BrewTaurus)
A6: 1 | B6: Brewhouse | C6: K220 2V: mash tun + boil kettle da 225 L, 7 kW, 2 pompe MP40, counterflow chiller, batch 150–190 L. Senza HLT: lo sparge richiede acqua calda separata | D6: V | E6: 1 | F6: 6999 | G6: =E6*F6 -> 6999 | H6: Prezzo letto sul sito
A7: 2 | B7: Fermentatori | C7: UT-200 PRO 200/260 L, 2,0 bar, PED Modulo H con dichiarazione di conformità per vaso, racking arm + spunding + pietra carbonatrice inclusi, camicia glicole. Servono 3 tank a rotazione per una cotta a settimana | D7: V | E7: =Parametri!$C$8 -> 3 | F7: 4490 | G7: =E7*F7 -> 13470 | H7: UT-200 4.490 € letto sul sito; su ordinazione (preventivo in 2 giorni)
A8: 3 | B8: Chiller glicole | C8: Quantor Chilly 25 M-LT 2,2 kW (scelto prudenzialmente per 3 tank da 200 L) | D8: V | E8: 1 | F8: 5349 | G8: =E8*F8 -> 5349 | H8: Prezzo letto sul sito. Voi lo comprereste usato: confermare la potenza con BrewTaurus
A9: 4 | B9: Collegamento glicole ai tank | C9: Tubo isolato, manifold mandata/ritorno e raccordi verso Ø31,8 mm TC dei tank | D9: S | E9: 1 | F9: 500 | G9: =E9*F9 -> 500 | H9: Stima mia
A10: 5 | B10: Impianto CIP | C10: CIP kit manuale (pompa 65 W, spray head rotante, raccordi TC): lavaggio in ricircolo con detergente e sanitizzante; l'acqua calda va preparata a parte | D10: V | E10: 1 | F10: 499 | G10: =E10*F10 -> 499 | H10: CIP kit 499 € letto sul sito
A11: 6 | B11: Hose Kit | C11: Tubo silicone alimentare alta temperatura 2 m + quick disconnect + raccordi 1.5" TC | D11: V | E11: 4 | F11: 109 | G11: =E11*F11 -> 436 | H11: Il K220 ha già molti raccordi: 4 è una stima
A12: 7 | B12: Controllo temperatura fermentatori | C12: Controller digitale + valvola glicole per ciascun tank | D12: S | E12: =Parametri!$C$8 -> 3 | F12: 130 | G12: =E12*F12 -> 390 | H12: Stima mia (Inkbird ITC-308 WiFi costa 79 €)
A13: 8 | B13: Quadro elettrico e controllo sala cottura | C13: Armadio IP54/65, sezionatore, magnetotermici/differenziali, SSR/contattori, PID/PLC, PT100, 24 V, pulsanti, emergenza, cablaggio (da far fare all'elettricista) | D13: S | E13: 1 | F13: 1200 | G13: =E13*F13 -> 1200 | H13: Stima mia: da verificare se il controller è incluso nel K220 2V
A14: 9 | B14: Counterflow chiller (se non incluso) | C14: Scambiatore mosto | D14: V | E14: 0 | F14: 0 | G14: =E14*F14 -> 0 | H14: Incluso nel K220 2V
A15: 10 | B15: Serbatoio acqua calda per sparge | C15: Con il K220 2V manca l'HLT: serve una fonte di acqua calda separata per lo sparge | D15: S | E15: 1 | F15: 250 | G15: =E15*F15 -> 250 | H15: Stima mia
A16: 11 | B16: Trasporto macchinari da Praga | C16: Consegna dei macchinari (pallet) o ritiro con furgone: non incluso nei prezzi BrewTaurus. Per scaricare i tank servono carrello elevatore o gru | D16: S | E16: 1 | F16: 1200 | G16: =E16*F16 -> 1200 | H16: Stima mia, non verificata: chiedere a BrewTaurus un preventivo con trasporto incluso e confrontarlo con il ritiro vostro (distanza circa 1.000 km)
B17: Subtotale A | G17: =SUM(G6:G16) -> 30293
A19: B. Lavorazione, strumenti e magazzino
A20: 12 | B20: Mulino per malto a rulli | C20: Macina il malto in sala cottura (necessario se compri malto intero) | D20: S | E20: 1 | F20: 1300 | G20: =E20*F20 -> 1300 | H20: Stima mia: BrewTaurus vende mulini ma non ho letto il prezzo
A21: 13 | B21: Pompa di ricambio MP-40RM | C21: Pompa magnetica 65 W (ricambio): non acquistata, si compra se si rompe | D21: V | E21: 0 | F21: 0 | G21: =E21*F21 -> 0 | H21: Prezzo letto, a volte non disponibile
A22: 14 | B22: Strumenti di controllo qualità | C22: Densimetro/rifrattometro, pH-metro, termometri, bilancia di precisione, vetreria | D22: S | E22: 1 | F22: 400 | G22: =E22*F22 -> 400 | H22: Stima mia, versione snella: già avete qualche strumento
A23: 15 | B23: Analisi di laboratorio iniziali | C23: Grado alcolico, estratto, microbiologia sulle prime cotte | D23: S | E23: 1 | F23: 300 | G23: =E23*F23 -> 300 | H23: Stima mia, versione snella
A24: 16 | B24: Trattamento acqua | C24: Filtri a carbone (niente addolcitore) | D24: S | E24: 1 | F24: 300 | G24: =E24*F24 -> 300 | H24: Stima mia: scelta vostra; l'acqua del locale non è stata analizzata
A25: 17 | B25: Scaffalature, transpallet, carrelli | C25: Stoccaggio malto, confezioni, vuoti | D25: S | E25: 1 | F25: 400 | G25: =E25*F25 -> 400 | H25: Stima mia, versione snella (locale da 40–80 m²)
B26: Subtotale B | G26: =SUM(G20:G25) -> 2700
A28: ="C. Confezionamento in fusti ("&ROUND(Parametri!C26*100,0)&"% del volume)" -> C. Confezionamento in fusti (80% del volume)
A29: 18 | B29: ="Fusti inox "&Parametri!C21&" L" -> Fusti inox 30 L | C29: Numero = min(capacità, domanda) × quota fusti ÷ capacità del fusto ÷ giri annui, almeno 10 | D29: S | E29: =MAX(10,ROUNDUP(MIN(Parametri!$C$16,Parametri!$C$25)*Parametri!$C$26/Parametri!$C$21/Parametri!$C$60,0)) -> 21 | F29: =Parametri!$C$59 -> 110 | G29: =E29*F29 -> 2310 | H29: Prezzo del fusto = stima mia; possibile cauzione ai clienti
A30: 19 | B30: Raccordi/coupler per fusti | C30: Testine A/S per riempimento e prelievo | D30: S | E30: 2 | F30: 110 | G30: =E30*F30 -> 220 | H30: Stima mia
A31: 20 | B31: Sistema di riempimento e lavaggio fusti | C31: Postazione manuale con CO2 e CIP fusti | D31: S | E31: 1 | F31: 600 | G31: =E31*F31 -> 600 | H31: Stima mia
A32: 21 | B32: CO2: bombola, riduttore, manometri | C32: Bombola 10 kg + regolatore + linee | D32: S | E32: 1 | F32: 300 | G32: =E32*F32 -> 300 | H32: Stima mia
A33: 22 | B33: Cella frigorifera per fusti | C33: Stoccaggio fusti pieni a bassa temperatura, abbastanza grande da contenere i fusti in circolazione | D33: S | E33: 1 | F33: 5500 | G33: =E33*F33 -> 5500 | H33: Voi la volete: stima mia, abbastanza grande per i fusti in circolazione (usata costerebbe meno). Non è obbligatoria: la birra può restare nei tank e i fusti si riempiono a ordine
B34: Subtotale C | G34: =SUM(G29:G33) -> 8930
A36: ="D. Imbottigliamento ("&ROUND(Parametri!C27*100,0)&"% del volume)" -> D. Imbottigliamento (20% del volume)
A37: 23 | B37: Riempitrice a contropressione | C37: 4 teste, riempie dal tank in pressione | D37: S | E37: 1 | F37: 1200 | G37: =E37*F37 -> 1200 | H37: Stima mia, versione snella (valutare usato)
A38: 24 | B38: Capsulatrice | C38: Tappi corona | D38: S | E38: 1 | F38: 250 | G38: =E38*F38 -> 250 | H38: Stima mia
A39: 25 | B39: Etichettatrice manuale | C39: Etichette autoadesive applicate a mano | D39: S | E39: 1 | F39: 300 | G39: =E39*F39 -> 300 | H39: Stima mia, versione snella
A40: 26 | B40: Risciacquatrice e casse/tavoli | C40: Pulizia bottiglie e movimentazione | D40: S | E40: 1 | F40: 200 | G40: =E40*F40 -> 200 | H40: Stima mia, versione snella
B41: Subtotale D | G41: =SUM(G37:G40) -> 1950
A43: E. Locale, utenze e impianti
A44: 27 | B44: Pavimento con pendenze e pozzetti | C44: Scarico a pavimento, resina lavabile | D44: S | E44: 1 | F44: 2500 | G44: =E44*F44 -> 2500 | H44: Stima mia
A45: 28 | B45: Rivestimenti lavabili pareti e porte | C45: Requisito igienico-sanitario | D45: S | E45: 1 | F45: 600 | G45: =E45*F45 -> 600 | H45: Pareti e imbiancatura le fate voi: solo materiali (stima mia)
A46: 29 | B46: Impianto idraulico e scarichi | C46: Allacci acqua calda/fredda, scarico, vasca di decantazione | D46: S | E46: 1 | F46: 2500 | G46: =E46*F46 -> 2500 | H46: Stima mia
A47: 30 | B47: Ventilazione vapori | C47: Finestra con ventola semplice (scelta vostra) | D47: S | E47: 1 | F47: 300 | G47: =E47*F47 -> 300 | H47: Stima mia: da verificare che basti per umidità e requisiti ASL. In alternativa condensatore vapori BrewTaurus (≈360 €) o canna di estrazione (≈1.800 €)
A48: 31 | B48: Allaccio elettrico trifase / potenziamento | C48: Oneri al distributore; potenza da verificare: contratto attuale sconosciuto. K220: 7–14 kW + chiller + cella frigorifera | D48: S | E48: 1 | F48: 1500 | G48: =E48*F48 -> 1500 | H48: Stima mia: chiedere preventivo al distributore
A49: 32 | B49: Impianto elettrico interno e linee dedicate | C49: Quadro generale, protezioni, linee per macchine | D49: S | E49: 1 | F49: 1250 | G49: =E49*F49 -> 1250 | H49: Avete un elettricista: stima 50% del costo
A50: 33 | B50: Antincendio e sicurezza | C50: Estintori, segnaletica, valutazione rischi; eventuale CPI se necessario | D50: S | E50: 1 | F50: 600 | G50: =E50*F50 -> 600 | H50: CPI solo sopra certe soglie (birrartigianale.com)
A51: 34 | B51: Progettazione e pratiche tecniche | C51: Planimetrie e pratiche tecniche | D51: S | E51: 1 | F51: 0 | G51: =E51*F51 -> 0 | H51: Se ne occupa il socio architetto (risparmio ≈1.500 €)
A52: 35 | B52: Cauzione sull'affitto | C52: Mesi di affitto da versare | D52: S | E52: =Parametri!$C$89 -> 0 | F52: =Parametri!$C$73 -> 0 | G52: =E52*F52 -> 0 | H52: Recuperabile a fine contratto
A53: 36 | B53: Riduzione per lavori già presenti nel locale | C53: Le voci da 'Pavimento' a 'Antincendio' sono moltiplicate per la quota di lavori necessari (Parametri). Il locale è da verificare | D53: S | E53: 1 | F53: =-SUM(G44:G50)*(1-Parametri!$C$97) -> 0 | G53: =E53*F53 -> 0 | H53: Stato del locale da verificare con il socio architetto
B54: Subtotale E | G54: =SUM(G44:G53) -> 9250
A56: F. Avvio, autorizzazioni e promozione
A57: 37 | B57: Costituzione SRL e Camera di Commercio | C57: Atto notarile, capitale sociale (verificare), ComUnica, ATECO 11.05.00 | D57: S | E57: 1 | F57: 1500 | G57: =E57*F57 -> 1500 | H57: Stima mia: notaio e adempimenti SRL; il capitale sociale da versare non è incluso
A58: 38 | B58: SCIA al SUAP + notifica sanitaria ASL | C58: Registrazione stabilimento alimentare (Reg. CE 852/2004) | D58: S | E58: 1 | F58: 300 | G58: =E58*F58 -> 300 | H58: Fate voi con il socio architetto: restano diritti di segreteria e bolli (stima mia, da verificare)
A59: 39 | B59: Piano HACCP e formazione | C59: Autocontrollo e tracciabilità (Reg. CE 178/2002) | D59: S | E59: 1 | F59: 300 | G59: =E59*F59 -> 300 | H59: Piano scritto da voi (con la formazione obbligatoria): stima mia per corsi e materiali. Rischio di errori: farlo verificare
A60: 40 | B60: Licenza ADM (deposito fiscale/microbirrificio) | C60: Diritti di licenza + pratica; codice accisa; registri di carico/scarico | D60: S | E60: 1 | F60: 500 | G60: =E60*F60 -> 500 | H60: Pratica fatta da voi: restano diritti e bolli (stima mia). Chiedere al commercialista di controllare registri e dichiarazioni accise
A61: 41 | B61: Fideiussione/cauzione ADM (primo anno) | C61: Calcolata da ADM sulla capacità dei serbatoi | D61: S | E61: 1 | F61: 500 | G61: =E61*F61 -> 500 | H61: Stima mia; l'importo reale lo fissa ADM
A62: 42 | B62: Commercialista e consulenza di avvio | C62: Scelta regime fiscale, apertura pratiche | D62: S | E62: 1 | F62: 500 | G62: =E62*F62 -> 500 | H62: Stima mia
A63: 43 | B63: Marchio, logo e grafica etichette | C63: Registrazione marchio, design | D63: S | E63: 1 | F63: 300 | G63: =E63*F63 -> 300 | H63: Logo ed etichette le fate voi: solo registrazione del marchio (stima mia, da verificare)
A64: 44 | B64: Sito web e foto | C64: Vetrina base | D64: S | E64: 1 | F64: 100 | G64: =E64*F64 -> 100 | H64: Il sito lo fa il socio ingegnere informatico: dominio, hosting e foto (stima mia)
A65: 45 | B65: Marketing di lancio e campionature | C65: Assaggi, eventi | D65: S | E65: 1 | F65: 300 | G65: =E65*F65 -> 300 | H65: Stima mia, versione snella: solo campionature per i primi eventi
B66: Subtotale F | G66: =SUM(G57:G65) -> 4300
A68: G. Totali
B69: Risparmio per attrezzatura usata | C69: Sconto (parametro) sulle voci che comprereste usate: chiller, mulino, pompe, strumenti, scaffalature, riempitrice e capsulatrice, coupler e sistema fusti | G69: =-(G8+G20+G21+G22+G25+G30+G31+G37+G38)*Parametri!$C$96 -> -3887.6
B70: Investimento A–F (macchine, locale, avvio) | G70: =G17+G26+G34+G41+G54+G66+G69 -> 53535.4
B71: Imprevisti | C71: % sulle voci A–F (parametro) | G71: =G70*Parametri!$C$95 -> 5353.54
B72: Capitale circolante iniziale | C72: Mesi di costi (variabili + fissi) dell'anno 1: malto, luppolo, imballaggi, affitto, ecc. | G72: =Parametri!$C$94/12*('Business plan'!C27+'Business plan'!C42) -> 1422.7512
B73: TOTALE INVESTIMENTO | G73: =G70+G71+G72 -> 60311.691
A75: Nota IVA: i prezzi sono senza IVA. Con partita IVA in regime ordinario l'IVA sugli acquisti è detraibile; in regime forfettario non lo è (verificare con un commercialista).

Sheet Materie prime
A1: Materie prime e ricette tipo
A2: Stime di consumo per stile e prezzi di acquisto. Da validare con ricette reali e preventivi dei fornitori.
A4: Stile | B4: Quota mix | C4: °Plato | D4: Malto (kg/hl) | E4: Prezzo malto (€/kg) | F4: Luppolo (g/hl) | G4: Prezzo luppolo (€/kg) | H4: Lievito (€/hl) | I4: Additivi/sali (€/hl) | J4: Costo malto (€/hl) | K4: Costo luppolo (€/hl) | L4: Costo totale (€/hl)
A5: Pils / Blonde (leggera, bevibile) | B5: 0.4 | C5: 12 | D5: 20 | E5: 1.3 | F5: 120 | G5: 35 | H5: 3 | I5: 1.5 | J5: =D5*E5 -> 26 | K5: =F5/1000*G5 -> 4.2 | L5: =J5+K5+H5+I5 -> 34.7
A6: Pale Ale / APA | B6: 0.35 | C6: 14 | D6: 23 | E6: 1.4 | F6: 300 | G6: 40 | H6: 4 | I6: 1.5 | J6: =D6*E6 -> 32.2 | K6: =F6/1000*G6 -> 12 | L6: =J6+K6+H6+I6 -> 49.7
A7: IPA (luppolata) | B7: 0.25 | C7: 16 | D7: 26 | E7: 1.5 | F7: 700 | G7: 45 | H7: 4.5 | I7: 1.5 | J7: =D7*E7 -> 39 | K7: =F7/1000*G7 -> 31.5 | L7: =J7+K7+H7+I7 -> 76.5
A9: Media pesata | B9: =SUM(B5:B7) -> 1 | C9: =SUMPRODUCT(B5:B7,C5:C7) -> 13.7 | L9: =SUMPRODUCT(B5:B7,L5:L7) -> 50.4
A10: Controllo: la quota mix deve fare 100%. Il costo medio per ettolitro va confrontato con i 30–60 €/hl citati da La Casetta Craft Beer Crew (variabile secondo ingredienti).
A12: Fabbisogno per una cotta dello scenario K220 (litri da Parametri)
A13: Stile | B13: Litri cotta | C13: Malto (kg) | D13: Malto (€) | E13: Luppolo (g) | F13: Luppolo (€) | G13: Lievito+additivi (€) | H13: Totale cotta (€) | I13: Costo materie prime (€/L)
A14: =A5 -> Pils / Blonde (leggera, bevibile) | B14: =Parametri!$C$7 -> 180 | C14: =D5*B14/100 -> 36 | D14: =C14*E5 -> 46.8 | E14: =F5*B14/100 -> 216 | F14: =E14/1000*G5 -> 7.56 | G14: =(H5+I5)*B14/100 -> 8.1 | H14: =D14+F14+G14 -> 62.46 | I14: =H14/B14 -> 0.347
A15: =A6 -> Pale Ale / APA | B15: =Parametri!$C$7 -> 180 | C15: =D6*B15/100 -> 41.4 | D15: =C15*E6 -> 57.96 | E15: =F6*B15/100 -> 540 | F15: =E15/1000*G6 -> 21.6 | G15: =(H6+I6)*B15/100 -> 9.9 | H15: =D15+F15+G15 -> 89.46 | I15: =H15/B15 -> 0.497
A16: =A7 -> IPA (luppolata) | B16: =Parametri!$C$7 -> 180 | C16: =D7*B16/100 -> 46.8 | D16: =C16*E7 -> 70.2 | E16: =F7*B16/100 -> 1260 | F16: =E16/1000*G7 -> 56.7 | G16: =(H7+I7)*B16/100 -> 10.8 | H16: =D16+F16+G16 -> 137.7 | I16: =H16/B16 -> 0.765
A18: Dove comprare e come acquistare (da verificare con preventivi)
A19: • Malto: sacchi da 25 kg o big bag, base pilsner 1,0–2,0 €/kg a seconda di quantità e fornitore (La Casetta Craft Beer Crew); malti speciali anche oltre 3 €/kg.
A20: • Luppolo: pellet in buste da 1 kg; varietà moderne (Citra, Mosaic, Nelson Sauvin) 6–8 € all'etto (La Casetta); varietà classiche 20–50 €/kg.
A21: • Lievito: secco o liquido; il lievito liquido costa di più (10–15 € a dose secondo ilmiobusinessplan.com).
A22: • Acqua: potenzialmente da addolcire/filtrare; correttivi (sali, acido lattico) tra gli additivi.
A23: • Detergenti: caustico (5–10 kg iniziali), acido (≈5 L), sanitizzante (1–2 L): sono compresi nella voce Detergenti dei Parametri.
A24: • Scorte: tenere circa 2 mesi di malto/luppolo; il malto va conservato asciutto, il luppolo in freezer.

Sheet Business plan
A1: Business plan a 15 anni – K220
A2: ="Scenario: "&Parametri!$C$6 -> Scenario: K220 2V + 3×UT-200
A4: Voce (valori reali, € salvo diversa indicazione) | B4: Anno 0 | C4: Anno 1 | D4: Anno 2 | E4: Anno 3 | F4: Anno 4 | G4: Anno 5 | H4: Anno 6 | I4: Anno 7 | J4: Anno 8 | K4: Anno 9 | L4: Anno 10 | M4: Anno 11 | N4: Anno 12 | O4: Anno 13 | P4: Anno 14 | Q4: Anno 15
A5: Domanda raggiunta (% del volume a regime) | C5: =Parametri!$C$39 -> 0.4 | D5: =Parametri!$C$40 -> 0.65 | E5: =Parametri!$C$41 -> 0.85 | F5: =Parametri!$C$42 -> 1 | G5: =Parametri!$C$43 -> 1 | H5: =Parametri!$C$43 -> 1 | I5: =Parametri!$C$43 -> 1 | J5: =Parametri!$C$43 -> 1 | K5: =Parametri!$C$43 -> 1 | L5: =Parametri!$C$43 -> 1 | M5: =Parametri!$C$43 -> 1 | N5: =Parametri!$C$43 -> 1 | ... Q5: =Parametri!$C$43 -> 1
A6: Capacità produttiva (L/anno) | C6: =Parametri!$C$16 -> 8280 | D6: =Parametri!$C$16 -> 8280 | E6: =Parametri!$C$16 -> 8280 | F6: =Parametri!$C$16 -> 8280 | G6: =Parametri!$C$16 -> 8280 | H6: =Parametri!$C$16 -> 8280 | I6: =Parametri!$C$16 -> 8280 | J6: =Parametri!$C$16 -> 8280 | ... Q6: =Parametri!$C$16 -> 8280
A7: Produzione (L): minimo tra capacità e domanda | C7: =MIN(C6,Parametri!$C$25*C5/(1-Parametri!$C$28)) -> 2253.75 | D7: =MIN(D6,Parametri!$C$25*D5/(1-Parametri!$C$28)) -> 3662.3438 | E7: =MIN(E6,Parametri!$C$25*E5/(1-Parametri!$C$28)) -> 4789.2188 | F7: =MIN(F6,Parametri!$C$25*F5/(1-Parametri!$C$28)) -> 5634.375 | G7: =MIN(G6,Parametri!$C$25*G5/(1-Parametri!$C$28)) -> 5634.375 | H7: =MIN(H6,Parametri!$C$25*H5/(1-Parametri!$C$28)) -> 5634.375 | I7: =MIN(I6,Parametri!$C$25*I5/(1-Parametri!$C$28)) -> 5634.375 | J7: =MIN(J6,Parametri!$C$25*J5/(1-Parametri!$C$28)) -> 5634.375 | ... Q7: =MIN(Q6,Parametri!$C$25*Q5/(1-Parametri!$C$28)) -> 5634.375
A8: Vendite (L, dopo le perdite) | C8: =C7*(1-Parametri!$C$28) -> 2163.6 | D8: =D7*(1-Parametri!$C$28) -> 3515.85 | E8: =E7*(1-Parametri!$C$28) -> 4597.65 | F8: =F7*(1-Parametri!$C$28) -> 5409 | G8: =G7*(1-Parametri!$C$28) -> 5409 | H8: =H7*(1-Parametri!$C$28) -> 5409 | I8: =I7*(1-Parametri!$C$28) -> 5409 | J8: =J7*(1-Parametri!$C$28) -> 5409 | ... Q8: =Q7*(1-Parametri!$C$28) -> 5409
A9: di cui in fusti (L) | C9: =C8*Parametri!$C$26 -> 1728 | D9: =D8*Parametri!$C$26 -> 2808 | E9: =E8*Parametri!$C$26 -> 3672 | F9: =F8*Parametri!$C$26 -> 4320 | G9: =G8*Parametri!$C$26 -> 4320 | H9: =H8*Parametri!$C$26 -> 4320 | I9: =I8*Parametri!$C$26 -> 4320 | J9: =J8*Parametri!$C$26 -> 4320 | ... Q9: =Q8*Parametri!$C$26 -> 4320
A10: di cui in bottiglia (L) | C10: =C8*Parametri!$C$27 -> 435.6 | D10: =D8*Parametri!$C$27 -> 707.85 | E10: =E8*Parametri!$C$27 -> 925.65 | F10: =F8*Parametri!$C$27 -> 1089 | G10: =G8*Parametri!$C$27 -> 1089 | H10: =H8*Parametri!$C$27 -> 1089 | I10: =I8*Parametri!$C$27 -> 1089 | J10: =J8*Parametri!$C$27 -> 1089 | ... Q10: =Q8*Parametri!$C$27 -> 1089
A11: Bottiglie vendute (n) | C11: =C10/Parametri!$C$38 -> 1320 | D11: =D10/Parametri!$C$38 -> 2145 | E11: =E10/Parametri!$C$38 -> 2805 | F11: =F10/Parametri!$C$38 -> 3300 | G11: =G10/Parametri!$C$38 -> 3300 | H11: =H10/Parametri!$C$38 -> 3300 | I11: =I10/Parametri!$C$38 -> 3300 | J11: =J10/Parametri!$C$38 -> 3300 | ... Q11: =Q10/Parametri!$C$38 -> 3300
A12: Cotte all'anno (n) | C12: =C7/Parametri!$C$7 -> 12.520833 | D12: =D7/Parametri!$C$7 -> 20.346354 | E12: =E7/Parametri!$C$7 -> 26.606771 | F12: =F7/Parametri!$C$7 -> 31.302083 | G12: =G7/Parametri!$C$7 -> 31.302083 | H12: =H7/Parametri!$C$7 -> 31.302083 | I12: =I7/Parametri!$C$7 -> 31.302083 | J12: =J7/Parametri!$C$7 -> 31.302083 | ... Q12: =Q7/Parametri!$C$7 -> 31.302083
A13: Utilizzo della capacità produttiva | C13: =IF(C6=0,0,C7/C6) -> 0.27219203 | D13: =IF(D6=0,0,D7/D6) -> 0.44231205 | E13: =IF(E6=0,0,E7/E6) -> 0.57840806 | F13: =IF(F6=0,0,F7/F6) -> 0.68048007 | G13: =IF(G6=0,0,G7/G6) -> 0.68048007 | H13: =IF(H6=0,0,H7/H6) -> 0.68048007 | I13: =IF(I6=0,0,I7/I6) -> 0.68048007 | J13: =IF(J6=0,0,J7/J6) -> 0.68048007 | ... Q13: =IF(Q6=0,0,Q7/Q6) -> 0.68048007
A14: RICAVI
A15: Ricavi fusti | C15: =C9*Parametri!$C$36 -> 6912 | D15: =D9*Parametri!$C$36 -> 11232 | E15: =E9*Parametri!$C$36 -> 14688 | F15: =F9*Parametri!$C$36 -> 17280 | G15: =G9*Parametri!$C$36 -> 17280 | H15: =H9*Parametri!$C$36 -> 17280 | I15: =I9*Parametri!$C$36 -> 17280 | J15: =J9*Parametri!$C$36 -> 17280 | ... Q15: =Q9*Parametri!$C$36 -> 17280
A16: Ricavi bottiglie | C16: =C11*Parametri!$C$37 -> 2640 | D16: =D11*Parametri!$C$37 -> 4290 | E16: =E11*Parametri!$C$37 -> 5610 | F16: =F11*Parametri!$C$37 -> 6600 | G16: =G11*Parametri!$C$37 -> 6600 | H16: =H11*Parametri!$C$37 -> 6600 | I16: =I11*Parametri!$C$37 -> 6600 | J16: =J11*Parametri!$C$37 -> 6600 | ... Q16: =Q11*Parametri!$C$37 -> 6600
A17: Ricavi totali (IVA esclusa) | C17: =C15+C16 -> 9552 | D17: =D15+D16 -> 15522 | E17: =E15+E16 -> 20298 | F17: =F15+F16 -> 23880 | G17: =G15+G16 -> 23880 | H17: =H15+H16 -> 23880 | I17: =I15+I16 -> 23880 | J17: =J15+J16 -> 23880 | ... Q17: =Q15+Q16 -> 23880
A18: COSTI VARIABILI
A19: Materie prime | C19: =C7/100*Parametri!$C$45 -> 1135.89 | D19: =D7/100*Parametri!$C$45 -> 1845.8212 | E19: =E7/100*Parametri!$C$45 -> 2413.7663 | F19: =F7/100*Parametri!$C$45 -> 2839.725 | G19: =G7/100*Parametri!$C$45 -> 2839.725 | H19: =H7/100*Parametri!$C$45 -> 2839.725 | I19: =I7/100*Parametri!$C$45 -> 2839.725 | J19: =J7/100*Parametri!$C$45 -> 2839.725 | ... Q19: =Q7/100*Parametri!$C$45 -> 2839.725
A20: Detergenti e sanitizzanti | C20: =C7/100*Parametri!$C$46 -> 90.15 | D20: =D7/100*Parametri!$C$46 -> 146.49375 | E20: =E7/100*Parametri!$C$46 -> 191.56875 | F20: =F7/100*Parametri!$C$46 -> 225.375 | G20: =G7/100*Parametri!$C$46 -> 225.375 | H20: =H7/100*Parametri!$C$46 -> 225.375 | I20: =I7/100*Parametri!$C$46 -> 225.375 | J20: =J7/100*Parametri!$C$46 -> 225.375 | ... Q20: =Q7/100*Parametri!$C$46 -> 225.375
A21: Energia elettrica | C21: =C7/100*Parametri!$C$48*Parametri!$C$49 -> 281.71875 | D21: =D7/100*Parametri!$C$48*Parametri!$C$49 -> 457.79297 | E21: =E7/100*Parametri!$C$48*Parametri!$C$49 -> 598.65234 | F21: =F7/100*Parametri!$C$48*Parametri!$C$49 -> 704.29688 | G21: =G7/100*Parametri!$C$48*Parametri!$C$49 -> 704.29688 | H21: =H7/100*Parametri!$C$48*Parametri!$C$49 -> 704.29688 | I21: =I7/100*Parametri!$C$48*Parametri!$C$49 -> 704.29688 | J21: =J7/100*Parametri!$C$48*Parametri!$C$49 -> 704.29688 | ... Q21: =Q7/100*Parametri!$C$48*Parametri!$C$49 -> 704.29688
A22: Acqua e fognatura | C22: =C7/100*Parametri!$C$50*Parametri!$C$51 -> 40.5675 | D22: =D7/100*Parametri!$C$50*Parametri!$C$51 -> 65.922188 | E22: =E7/100*Parametri!$C$50*Parametri!$C$51 -> 86.205938 | F22: =F7/100*Parametri!$C$50*Parametri!$C$51 -> 101.41875 | G22: =G7/100*Parametri!$C$50*Parametri!$C$51 -> 101.41875 | H22: =H7/100*Parametri!$C$50*Parametri!$C$51 -> 101.41875 | I22: =I7/100*Parametri!$C$50*Parametri!$C$51 -> 101.41875 | J22: =J7/100*Parametri!$C$50*Parametri!$C$51 -> 101.41875 | ... Q22: =Q7/100*Parametri!$C$50*Parametri!$C$51 -> 101.41875
A23: Imballaggi bottiglie (vetro, tappo, etichetta, cartone, CONAI) | C23: =C11*(Parametri!$C$52+Parametri!$C$53+Parametri!$C$54+Parametri!$C$55+Parametri!$C$56) -> 442.2 | D23: =D11*(Parametri!$C$52+Parametri!$C$53+Parametri!$C$54+Parametri!$C$55+Parametri!$C$56) -> 718.575 | E23: =E11*(Parametri!$C$52+Parametri!$C$53+Parametri!$C$54+Parametri!$C$55+Parametri!$C$56) -> 939.675 | F23: =F11*(Parametri!$C$52+Parametri!$C$53+Parametri!$C$54+Parametri!$C$55+Parametri!$C$56) -> 1105.5 | G23: =G11*(Parametri!$C$52+Parametri!$C$53+Parametri!$C$54+Parametri!$C$55+Parametri!$C$56) -> 1105.5 | H23: =H11*(Parametri!$C$52+Parametri!$C$53+Parametri!$C$54+Parametri!$C$55+Parametri!$C$56) -> 1105.5 | I23: =I11*(Parametri!$C$52+Parametri!$C$53+Parametri!$C$54+Parametri!$C$55+Parametri!$C$56) -> 1105.5 | J23: =J11*(Parametri!$C$52+Parametri!$C$53+Parametri!$C$54+Parametri!$C$55+Parametri!$C$56) -> 1105.5 | ... Q23: =Q11*(Parametri!$C$52+Parametri!$C$53+Parametri!$C$54+Parametri!$C$55+Parametri!$C$56) -> 1105.5
A24: Consumabili fusti (CO2, guarnizioni) | C24: =C9/100*Parametri!$C$57 -> 51.84 | D24: =D9/100*Parametri!$C$57 -> 84.24 | E24: =E9/100*Parametri!$C$57 -> 110.16 | F24: =F9/100*Parametri!$C$57 -> 129.6 | G24: =G9/100*Parametri!$C$57 -> 129.6 | H24: =H9/100*Parametri!$C$57 -> 129.6 | I24: =I9/100*Parametri!$C$57 -> 129.6 | J24: =J9/100*Parametri!$C$57 -> 129.6 | ... Q24: =Q9/100*Parametri!$C$57 -> 129.6
A25: Accisa sulla birra immessa in consumo | C25: =C8/100*Parametri!$C$47*Parametri!$C$62*(1-Parametri!$C$63) -> 529.9868 | D25: =D8/100*Parametri!$C$47*Parametri!$C$62*(1-Parametri!$C$63) -> 861.22855 | E25: =E8/100*Parametri!$C$47*Parametri!$C$62*(1-Parametri!$C$63) -> 1126.222 | F25: =F8/100*Parametri!$C$47*Parametri!$C$62*(1-Parametri!$C$63) -> 1324.967 | G25: =G8/100*Parametri!$C$47*Parametri!$C$62*(1-Parametri!$C$63) -> 1324.967 | H25: =H8/100*Parametri!$C$47*Parametri!$C$62*(1-Parametri!$C$63) -> 1324.967 | I25: =I8/100*Parametri!$C$47*Parametri!$C$62*(1-Parametri!$C$63) -> 1324.967 | J25: =J8/100*Parametri!$C$47*Parametri!$C$62*(1-Parametri!$C$63) -> 1324.967 | ... Q25: =Q8/100*Parametri!$C$47*Parametri!$C$62*(1-Parametri!$C$63) -> 1324.967
A26: Logistica e consegne | C26: =C17*Parametri!$C$58 -> 238.8 | D26: =D17*Parametri!$C$58 -> 388.05 | E26: =E17*Parametri!$C$58 -> 507.45 | F26: =F17*Parametri!$C$58 -> 597 | G26: =G17*Parametri!$C$58 -> 597 | H26: =H17*Parametri!$C$58 -> 597 | I26: =I17*Parametri!$C$58 -> 597 | J26: =J17*Parametri!$C$58 -> 597 | ... Q26: =Q17*Parametri!$C$58 -> 597
A27: Totale costi variabili | C27: =SUM(C19:C26) -> 2811.1531 | D27: =SUM(D19:D26) -> 4568.1237 | E27: =SUM(E19:E26) -> 5973.7002 | F27: =SUM(F19:F26) -> 7027.8826 | G27: =SUM(G19:G26) -> 7027.8826 | H27: =SUM(H19:H26) -> 7027.8826 | I27: =SUM(I19:I26) -> 7027.8826 | J27: =SUM(J19:J26) -> 7027.8826 | ... Q27: =SUM(Q19:Q26) -> 7027.8826
A28: Margine di contribuzione | C28: =C17-C27 -> 6740.8469 | D28: =D17-D27 -> 10953.876 | E28: =E17-E27 -> 14324.3 | F28: =F17-F27 -> 16852.117 | G28: =G17-G27 -> 16852.117 | H28: =H17-H27 -> 16852.117 | I28: =I17-I27 -> 16852.117 | J28: =J17-J27 -> 16852.117 | ... Q28: =Q17-Q27 -> 16852.117
A29: Margine di contribuzione % | C29: =IF(C17=0,0,C28/C17) -> 0.70570006 | D29: =IF(D17=0,0,D28/D17) -> 0.70570006 | E29: =IF(E17=0,0,E28/E17) -> 0.70570006 | F29: =IF(F17=0,0,F28/F17) -> 0.70570006 | G29: =IF(G17=0,0,G28/G17) -> 0.70570006 | H29: =IF(H17=0,0,H28/H17) -> 0.70570006 | I29: =IF(I17=0,0,I28/I17) -> 0.70570006 | J29: =IF(J17=0,0,J28/J17) -> 0.70570006 | ... Q29: =IF(Q17=0,0,Q28/Q17) -> 0.70570006
A30: COSTI FISSI
A31: Affitto locale | C31: =Parametri!$C$73*12 -> 0 | D31: =Parametri!$C$73*12 -> 0 | E31: =Parametri!$C$73*12 -> 0 | F31: =Parametri!$C$73*12 -> 0 | G31: =Parametri!$C$73*12 -> 0 | H31: =Parametri!$C$73*12 -> 0 | I31: =Parametri!$C$73*12 -> 0 | J31: =Parametri!$C$73*12 -> 0 | ... Q31: =Parametri!$C$73*12 -> 0
A32: Utenze fisse | C32: =Parametri!$C$74*12 -> 1440 | D32: =Parametri!$C$74*12 -> 1440 | E32: =Parametri!$C$74*12 -> 1440 | F32: =Parametri!$C$74*12 -> 1440 | G32: =Parametri!$C$74*12 -> 1440 | H32: =Parametri!$C$74*12 -> 1440 | I32: =Parametri!$C$74*12 -> 1440 | J32: =Parametri!$C$74*12 -> 1440 | ... Q32: =Parametri!$C$74*12 -> 1440
A33: Assicurazioni | C33: =Parametri!$C$75 -> 1500 | D33: =Parametri!$C$75 -> 1500 | E33: =Parametri!$C$75 -> 1500 | F33: =Parametri!$C$75 -> 1500 | G33: =Parametri!$C$75 -> 1500 | H33: =Parametri!$C$75 -> 1500 | I33: =Parametri!$C$75 -> 1500 | J33: =Parametri!$C$75 -> 1500 | ... Q33: =Parametri!$C$75 -> 1500
A34: Commercialista e consulenze | C34: =Parametri!$C$76 -> 500 | D34: =Parametri!$C$76 -> 500 | E34: =Parametri!$C$76 -> 500 | F34: =Parametri!$C$76 -> 500 | G34: =Parametri!$C$76 -> 500 | H34: =Parametri!$C$76 -> 500 | I34: =Parametri!$C$76 -> 500 | J34: =Parametri!$C$76 -> 500 | ... Q34: =Parametri!$C$76 -> 500
A35: Contributi INPS (tutte le persone che lavorano) | C35: =IF(Parametri!$C$77=0,0,Parametri!$C$77*(Parametri!$C$79*MIN(MAX(IF(Parametri!$C$64=1,C17*Parametri!$C$65,MAX(0,C28-(C31+C32+C33+C34+C36+C37+C38+C39+C40+C41)))/Parametri!$C$77,Parametri!$C$78),Parametri!$C$80)+Parametri!$C$81)*(1-IF(Parametri!$C$64=1,Parametri!$C$82,0))) -> 0 | D35: =IF(Parametri!$C$77=0,0,Parametri!$C$77*(Parametri!$C$79*MIN(MAX(IF(Parametri!$C$64=1,D17*Parametri!$C$65,MAX(0,D28-(D31+D32+D33+D34+D36+D37+D38+D39+D40+D41)))/Parametri!$C$77,Parametri!$C$78),Parametri!$C$80)+Parametri!$C$81)*(1-IF(Parametri!$C$64=1,Parametri!$C$82,0))) -> 0 | E35: =IF(Parametri!$C$77=0,0,Parametri!$C$77*(Parametri!$C$79*MIN(MAX(IF(Parametri!$C$64=1,E17*Parametri!$C$65,MAX(0,E28-(E31+E32+E33+E34+E36+E37+E38+E39+E40+E41)))/Parametri!$C$77,Parametri!$C$78),Parametri!$C$80)+Parametri!$C$81)*(1-IF(Parametri!$C$64=1,Parametri!$C$82,0))) -> 0 | F35: =IF(Parametri!$C$77=0,0,Parametri!$C$77*(Parametri!$C$79*MIN(MAX(IF(Parametri!$C$64=1,F17*Parametri!$C$65,MAX(0,F28-(F31+F32+F33+F34+F36+F37+F38+F39+F40+F41)))/Parametri!$C$77,Parametri!$C$78),Parametri!$C$80)+Parametri!$C$81)*(1-IF(Parametri!$C$64=1,Parametri!$C$82,0))) -> 0 | G35: =IF(Parametri!$C$77=0,0,Parametri!$C$77*(Parametri!$C$79*MIN(MAX(IF(Parametri!$C$64=1,G17*Parametri!$C$65,MAX(0,G28-(G31+G32+G33+G34+G36+G37+G38+G39+G40+G41)))/Parametri!$C$77,Parametri!$C$78),Parametri!$C$80)+Parametri!$C$81)*(1-IF(Parametri!$C$64=1,Parametri!$C$82,0))) -> 0 | H35: =IF(Parametri!$C$77=0,0,Parametri!$C$77*(Parametri!$C$79*MIN(MAX(IF(Parametri!$C$64=1,H17*Parametri!$C$65,MAX(0,H28-(H31+H32+H33+H34+H36+H37+H38+H39+H40+H41)))/Parametri!$C$77,Parametri!$C$78),Parametri!$C$80)+Parametri!$C$81)*(1-IF(Parametri!$C$64=1,Parametri!$C$82,0))) -> 0 | I35: =IF(Parametri!$C$77=0,0,Parametri!$C$77*(Parametri!$C$79*MIN(MAX(IF(Parametri!$C$64=1,I17*Parametri!$C$65,MAX(0,I28-(I31+I32+I33+I34+I36+I37+I38+I39+I40+I41)))/Parametri!$C$77,Parametri!$C$78),Parametri!$C$80)+Parametri!$C$81)*(1-IF(Parametri!$C$64=1,Parametri!$C$82,0))) -> 0 | J35: =IF(Parametri!$C$77=0,0,Parametri!$C$77*(Parametri!$C$79*MIN(MAX(IF(Parametri!$C$64=1,J17*Parametri!$C$65,MAX(0,J28-(J31+J32+J33+J34+J36+J37+J38+J39+J40+J41)))/Parametri!$C$77,Parametri!$C$78),Parametri!$C$80)+Parametri!$C$81)*(1-IF(Parametri!$C$64=1,Parametri!$C$82,0))) -> 0 | ... Q35: =IF(Parametri!$C$77=0,0,Parametri!$C$77*(Parametri!$C$79*MIN(MAX(IF(Parametri!$C$64=1,Q17*Parametri!$C$65,MAX(0,Q28-(Q31+Q32+Q33+Q34+Q36+Q37+Q38+Q39+Q40+Q41)))/Parametri!$C$77,Parametri!$C$78),Parametri!$C$80)+Parametri!$C$81)*(1-IF(Parametri!$C$64=1,Parametri!$C$82,0))) -> 0
A36: Fideiussione ADM | C36: =Parametri!$C$83 -> 500 | D36: =Parametri!$C$83 -> 500 | E36: =Parametri!$C$83 -> 500 | F36: =Parametri!$C$83 -> 500 | G36: =Parametri!$C$83 -> 500 | H36: =Parametri!$C$83 -> 500 | I36: =Parametri!$C$83 -> 500 | J36: =Parametri!$C$83 -> 500 | ... Q36: =Parametri!$C$83 -> 500
A37: Marketing e commerciale | C37: =Parametri!$C$84 -> 0 | D37: =Parametri!$C$84 -> 0 | E37: =Parametri!$C$84 -> 0 | F37: =Parametri!$C$84 -> 0 | G37: =Parametri!$C$84 -> 0 | H37: =Parametri!$C$84 -> 0 | I37: =Parametri!$C$84 -> 0 | J37: =Parametri!$C$84 -> 0 | ... Q37: =Parametri!$C$84 -> 0
A38: Manutenzione e ricambi | C38: =Parametri!$C$85*'Impianto e costi'!$G$70 -> 535.354 | D38: =Parametri!$C$85*'Impianto e costi'!$G$70 -> 535.354 | E38: =Parametri!$C$85*'Impianto e costi'!$G$70 -> 535.354 | F38: =Parametri!$C$85*'Impianto e costi'!$G$70 -> 535.354 | G38: =Parametri!$C$85*'Impianto e costi'!$G$70 -> 535.354 | H38: =Parametri!$C$85*'Impianto e costi'!$G$70 -> 535.354 | I38: =Parametri!$C$85*'Impianto e costi'!$G$70 -> 535.354 | J38: =Parametri!$C$85*'Impianto e costi'!$G$70 -> 535.354 | ... Q38: =Parametri!$C$85*'Impianto e costi'!$G$70 -> 535.354
A39: Analisi di laboratorio | C39: =Parametri!$C$86 -> 250 | D39: =Parametri!$C$86 -> 250 | E39: =Parametri!$C$86 -> 250 | F39: =Parametri!$C$86 -> 250 | G39: =Parametri!$C$86 -> 250 | H39: =Parametri!$C$86 -> 250 | I39: =Parametri!$C$86 -> 250 | J39: =Parametri!$C$86 -> 250 | ... Q39: =Parametri!$C$86 -> 250
A40: Rifiuti, abbonamenti, varie | C40: =Parametri!$C$87 -> 1000 | D40: =Parametri!$C$87 -> 1000 | E40: =Parametri!$C$87 -> 1000 | F40: =Parametri!$C$87 -> 1000 | G40: =Parametri!$C$87 -> 1000 | H40: =Parametri!$C$87 -> 1000 | I40: =Parametri!$C$87 -> 1000 | J40: =Parametri!$C$87 -> 1000 | ... Q40: =Parametri!$C$87 -> 1000
A41: Personale dipendente | C41: =Parametri!$C$88 -> 0 | D41: =Parametri!$C$88 -> 0 | E41: =Parametri!$C$88 -> 0 | F41: =Parametri!$C$88 -> 0 | G41: =Parametri!$C$88 -> 0 | H41: =Parametri!$C$88 -> 0 | I41: =Parametri!$C$88 -> 0 | J41: =Parametri!$C$88 -> 0 | ... Q41: =Parametri!$C$88 -> 0
A42: Totale costi fissi | C42: =SUM(C31:C41) -> 5725.354 | D42: =SUM(D31:D41) -> 5725.354 | E42: =SUM(E31:E41) -> 5725.354 | F42: =SUM(F31:F41) -> 5725.354 | G42: =SUM(G31:G41) -> 5725.354 | H42: =SUM(H31:H41) -> 5725.354 | I42: =SUM(I31:I41) -> 5725.354 | J42: =SUM(J31:J41) -> 5725.354 | ... Q42: =SUM(Q31:Q41) -> 5725.354
A43: EBITDA (margine operativo) | C43: =C28-C42 -> 1015.4929 | D43: =D28-D42 -> 5228.5223 | E43: =E28-E42 -> 8598.9458 | F43: =F28-F42 -> 11126.763 | G43: =G28-G42 -> 11126.763 | H43: =H28-H42 -> 11126.763 | I43: =I28-I42 -> 11126.763 | J43: =J28-J42 -> 11126.763 | ... Q43: =Q28-Q42 -> 11126.763
A44: Ammortamenti (impianti 10 anni, fusti 6 anni: poi zero) | C44: =IF(COLUMNS($C44:C44)<=Parametri!$C$70,('Impianto e costi'!$G$70-'Impianto e costi'!$G$29)/Parametri!$C$70,0)+IF(COLUMNS($C44:C44)<=Parametri!$C$71,'Impianto e costi'!$G$29/Parametri!$C$71,0) -> 5507.54 | D44: =IF(COLUMNS($C44:D44)<=Parametri!$C$70,('Impianto e costi'!$G$70-'Impianto e costi'!$G$29)/Parametri!$C$70,0)+IF(COLUMNS($C44:D44)<=Parametri!$C$71,'Impianto e costi'!$G$29/Parametri!$C$71,0) -> 5507.54 | E44: =IF(COLUMNS($C44:E44)<=Parametri!$C$70,('Impianto e costi'!$G$70-'Impianto e costi'!$G$29)/Parametri!$C$70,0)+IF(COLUMNS($C44:E44)<=Parametri!$C$71,'Impianto e costi'!$G$29/Parametri!$C$71,0) -> 5507.54 | F44: =IF(COLUMNS($C44:F44)<=Parametri!$C$70,('Impianto e costi'!$G$70-'Impianto e costi'!$G$29)/Parametri!$C$70,0)+IF(COLUMNS($C44:F44)<=Parametri!$C$71,'Impianto e costi'!$G$29/Parametri!$C$71,0) -> 5507.54 | G44: =IF(COLUMNS($C44:G44)<=Parametri!$C$70,('Impianto e costi'!$G$70-'Impianto e costi'!$G$29)/Parametri!$C$70,0)+IF(COLUMNS($C44:G44)<=Parametri!$C$71,'Impianto e costi'!$G$29/Parametri!$C$71,0) -> 5507.54 | H44: =IF(COLUMNS($C44:H44)<=Parametri!$C$70,('Impianto e costi'!$G$70-'Impianto e costi'!$G$29)/Parametri!$C$70,0)+IF(COLUMNS($C44:H44)<=Parametri!$C$71,'Impianto e costi'!$G$29/Parametri!$C$71,0) -> 5507.54 | I44: =IF(COLUMNS($C44:I44)<=Parametri!$C$70,('Impianto e costi'!$G$70-'Impianto e costi'!$G$29)/Parametri!$C$70,0)+IF(COLUMNS($C44:I44)<=Parametri!$C$71,'Impianto e costi'!$G$29/Parametri!$C$71,0) -> 5122.54 | J44: =IF(COLUMNS($C44:J44)<=Parametri!$C$70,('Impianto e costi'!$G$70-'Impianto e costi'!$G$29)/Parametri!$C$70,0)+IF(COLUMNS($C44:J44)<=Parametri!$C$71,'Impianto e costi'!$G$29/Parametri!$C$71,0) -> 5122.54 | ... Q44: =IF(COLUMNS($C44:Q44)<=Parametri!$C$70,('Impianto e costi'!$G$70-'Impianto e costi'!$G$29)/Parametri!$C$70,0)+IF(COLUMNS($C44:Q44)<=Parametri!$C$71,'Impianto e costi'!$G$29/Parametri!$C$71,0) -> 0
A45: EBIT | C45: =C43-C44 -> -4492.0471 | D45: =D43-D44 -> -279.01771 | E45: =E43-E44 -> 3091.4058 | F45: =F43-F44 -> 5619.2234 | G45: =G43-G44 -> 5619.2234 | H45: =H43-H44 -> 5619.2234 | I45: =I43-I44 -> 6004.2234 | J45: =J43-J44 -> 6004.2234 | ... Q45: =Q43-Q44 -> 11126.763
A46: Imposte (secondo il regime scelto) | C46: =IF(Parametri!$C$64=1,MAX(0,C17*Parametri!$C$65-C35)*Parametri!$C$66,MAX(0,C45)*(Parametri!$C$68+Parametri!$C$69)) -> 0 | D46: =IF(Parametri!$C$64=1,MAX(0,D17*Parametri!$C$65-D35)*Parametri!$C$66,MAX(0,D45)*(Parametri!$C$68+Parametri!$C$69)) -> 0 | E46: =IF(Parametri!$C$64=1,MAX(0,E17*Parametri!$C$65-E35)*Parametri!$C$66,MAX(0,E45)*(Parametri!$C$68+Parametri!$C$69)) -> 862.50221 | F46: =IF(Parametri!$C$64=1,MAX(0,F17*Parametri!$C$65-F35)*Parametri!$C$66,MAX(0,F45)*(Parametri!$C$68+Parametri!$C$69)) -> 1567.7633 | G46: =IF(Parametri!$C$64=1,MAX(0,G17*Parametri!$C$65-G35)*Parametri!$C$66,MAX(0,G45)*(Parametri!$C$68+Parametri!$C$69)) -> 1567.7633 | H46: =IF(Parametri!$C$64=1,MAX(0,H17*Parametri!$C$65-H35)*Parametri!$C$66,MAX(0,H45)*(Parametri!$C$68+Parametri!$C$69)) -> 1567.7633 | I46: =IF(Parametri!$C$64=1,MAX(0,I17*Parametri!$C$65-I35)*Parametri!$C$66,MAX(0,I45)*(Parametri!$C$68+Parametri!$C$69)) -> 1675.1783 | J46: =IF(Parametri!$C$64=1,MAX(0,J17*Parametri!$C$65-J35)*Parametri!$C$66,MAX(0,J45)*(Parametri!$C$68+Parametri!$C$69)) -> 1675.1783 | ... Q46: =IF(Parametri!$C$64=1,MAX(0,Q17*Parametri!$C$65-Q35)*Parametri!$C$66,MAX(0,Q45)*(Parametri!$C$68+Parametri!$C$69)) -> 3104.367
A47: Utile netto | C47: =C45-C46 -> -4492.0471 | D47: =D45-D46 -> -279.01771 | E47: =E45-E46 -> 2228.9036 | F47: =F45-F46 -> 4051.4601 | G47: =G45-G46 -> 4051.4601 | H47: =H45-H46 -> 4051.4601 | I47: =I45-I46 -> 4329.045 | J47: =J45-J46 -> 4329.045 | ... Q47: =Q45-Q46 -> 8022.3964
A48: Controllo limite ricavi forfettario | C48: =IF(AND(Parametri!$C$64=1,C17>Parametri!$C$67),"OLTRE LIMITE","ok") -> ok | D48: =IF(AND(Parametri!$C$64=1,D17>Parametri!$C$67),"OLTRE LIMITE","ok") -> ok | E48: =IF(AND(Parametri!$C$64=1,E17>Parametri!$C$67),"OLTRE LIMITE","ok") -> ok | F48: =IF(AND(Parametri!$C$64=1,F17>Parametri!$C$67),"OLTRE LIMITE","ok") -> ok | G48: =IF(AND(Parametri!$C$64=1,G17>Parametri!$C$67),"OLTRE LIMITE","ok") -> ok | H48: =IF(AND(Parametri!$C$64=1,H17>Parametri!$C$67),"OLTRE LIMITE","ok") -> ok | I48: =IF(AND(Parametri!$C$64=1,I17>Parametri!$C$67),"OLTRE LIMITE","ok") -> ok | J48: =IF(AND(Parametri!$C$64=1,J17>Parametri!$C$67),"OLTRE LIMITE","ok") -> ok | ... Q48: =IF(AND(Parametri!$C$64=1,Q17>Parametri!$C$67),"OLTRE LIMITE","ok") -> ok
A49: Ore di lavoro all'anno in due (stima, non valorizzate) | C49: =C12*Parametri!$C$91+C8/100*Parametri!$C$92 -> 179.29833 | D49: =D12*Parametri!$C$91+D8/100*Parametri!$C$92 -> 291.35979 | E49: =E12*Parametri!$C$91+E8/100*Parametri!$C$92 -> 381.00896 | F49: =F12*Parametri!$C$91+F8/100*Parametri!$C$92 -> 448.24583 | G49: =G12*Parametri!$C$91+G8/100*Parametri!$C$92 -> 448.24583 | H49: =H12*Parametri!$C$91+H8/100*Parametri!$C$92 -> 448.24583 | I49: =I12*Parametri!$C$91+I8/100*Parametri!$C$92 -> 448.24583 | J49: =J12*Parametri!$C$91+J8/100*Parametri!$C$92 -> 448.24583 | ... Q49: =Q12*Parametri!$C$91+Q8/100*Parametri!$C$92 -> 448.24583
A52: FLUSSI DI CASSA E RIENTRO DELL'INVESTIMENTO
A53: Flusso di cassa (utile netto + ammortamenti; anno 0 = investimento totale) | B53: =-'Impianto e costi'!$G$73 -> -60311.691 | C53: =C47+C44 -> 1015.4929 | D53: =D47+D44 -> 5228.5223 | E53: =E47+E44 -> 7736.4436 | F53: =F47+F44 -> 9559.0001 | G53: =G47+G44 -> 9559.0001 | H53: =H47+H44 -> 9559.0001 | I53: =I47+I44 -> 9451.585 | J53: =J47+J44 -> 9451.585 | ... Q53: =Q47+Q44 -> 8022.3964
A54: Flusso cumulato | B54: =B53 -> -60311.691 | C54: =B54+C53 -> -59296.198 | D54: =C54+D53 -> -54067.676 | E54: =D54+E53 -> -46331.232 | F54: =E54+F53 -> -36772.232 | G54: =F54+G53 -> -27213.232 | H54: =G54+H53 -> -17654.232 | I54: =H54+I53 -> -8202.6472 | J54: =I54+J53 -> 1248.9379 | ... Q54: =P54+Q53 -> 60264.09
A55: Calcolo del punto di rientro (supporto) | C55: =IF(AND(B54<0,C54>=0),0+(-B54)/C53,"") | D55: =IF(AND(C54<0,D54>=0),1+(-C54)/D53,"") | E55: =IF(AND(D54<0,E54>=0),2+(-D54)/E53,"") | F55: =IF(AND(E54<0,F54>=0),3+(-E54)/F53,"") | G55: =IF(AND(F54<0,G54>=0),4+(-F54)/G53,"") | H55: =IF(AND(G54<0,H54>=0),5+(-G54)/H53,"") | I55: =IF(AND(H54<0,I54>=0),6+(-H54)/I53,"") | J55: =IF(AND(I54<0,J54>=0),7+(-I54)/J53,"") -> 7.8678594 | K55: =IF(AND(J54<0,K54>=0),8+(-J54)/K53,"") | L55: =IF(AND(K54<0,L54>=0),9+(-K54)/L53,"") | M55: =IF(AND(L54<0,M54>=0),10+(-L54)/M53,"") | N55: =IF(AND(M54<0,N54>=0),11+(-M54)/N53,"") | O55: =IF(AND(N54<0,O54>=0),12+(-N54)/O53,"") | P55: =IF(AND(O54<0,P54>=0),13+(-O54)/P53,"") | Q55: =IF(AND(P54<0,Q54>=0),14+(-P54)/Q53,"")
A56: Payback senza mutuo (anni) | B56: =IF(COUNT(C55:Q55)=0,"oltre 15 anni: non rientra",MIN(C55:Q55)) -> 7.8678594
A58: Righe 4–56 (senza mutuo): il flusso di cassa è semplificato e non include variazioni del circolante né il valore residuo degli impianti. I ricavi sono ex IVA. Non sono previste sostituzioni di impianti e fusti: dopo l'anno 6 (fusti) e l'anno 10 (impianti) l'ammortamento finisce, ma le attrezzature andrebbero rinnovate.
A60: MUTUO E FLUSSI DI CASSA CON FINANZIAMENTO
A61: Debito a inizio anno | C61: =B66 -> 60311.691 | D61: =C66 -> 60311.691 | E61: =D66 -> 55993.474 | F61: =E66 -> 51363.093 | G61: =F66 -> 46397.981 | H61: =G66 -> 41073.94 | I61: =H66 -> 35365.025 | J61: =I66 -> 29243.411 | ... Q61: =P66 -> 0
A62: Mesi trascorsi dall'erogazione (a fine anno) | B62: 0 | C62: =B62+12 -> 12 | D62: =C62+12 -> 24 | E62: =D62+12 -> 36 | F62: =E62+12 -> 48 | G62: =F62+12 -> 60 | H62: =G62+12 -> 72 | I62: =H62+12 -> 84 | J62: =I62+12 -> 96 | ... Q62: =P62+12 -> 180
A63: Mesi di preammortamento (solo interessi) nell'anno | C63: =MAX(0,MIN(C62,Parametri!$C$104*12)-MIN(B62,Parametri!$C$104*12)) -> 12 | D63: =MAX(0,MIN(D62,Parametri!$C$104*12)-MIN(C62,Parametri!$C$104*12)) -> 0 | E63: =MAX(0,MIN(E62,Parametri!$C$104*12)-MIN(D62,Parametri!$C$104*12)) -> 0 | F63: =MAX(0,MIN(F62,Parametri!$C$104*12)-MIN(E62,Parametri!$C$104*12)) -> 0 | G63: =MAX(0,MIN(G62,Parametri!$C$104*12)-MIN(F62,Parametri!$C$104*12)) -> 0 | H63: =MAX(0,MIN(H62,Parametri!$C$104*12)-MIN(G62,Parametri!$C$104*12)) -> 0 | I63: =MAX(0,MIN(I62,Parametri!$C$104*12)-MIN(H62,Parametri!$C$104*12)) -> 0 | J63: =MAX(0,MIN(J62,Parametri!$C$104*12)-MIN(I62,Parametri!$C$104*12)) -> 0 | ... Q63: =MAX(0,MIN(Q62,Parametri!$C$104*12)-MIN(P62,Parametri!$C$104*12)) -> 0
A64: Mesi di ammortamento completati (a fine anno) | B64: 0 | C64: =MIN(Parametri!$C$103*12,MAX(0,C62-Parametri!$C$104*12)) -> 0 | D64: =MIN(Parametri!$C$103*12,MAX(0,D62-Parametri!$C$104*12)) -> 12 | E64: =MIN(Parametri!$C$103*12,MAX(0,E62-Parametri!$C$104*12)) -> 24 | F64: =MIN(Parametri!$C$103*12,MAX(0,F62-Parametri!$C$104*12)) -> 36 | G64: =MIN(Parametri!$C$103*12,MAX(0,G62-Parametri!$C$104*12)) -> 48 | H64: =MIN(Parametri!$C$103*12,MAX(0,H62-Parametri!$C$104*12)) -> 60 | I64: =MIN(Parametri!$C$103*12,MAX(0,I62-Parametri!$C$104*12)) -> 72 | J64: =MIN(Parametri!$C$103*12,MAX(0,J62-Parametri!$C$104*12)) -> 84 | ... Q64: =MIN(Parametri!$C$103*12,MAX(0,Q62-Parametri!$C$104*12)) -> 120
A65: Quota capitale rimborsata | C65: =C61-C66 -> 0 | D65: =D61-D66 -> 4318.2171 | E65: =E61-E66 -> 4630.3814 | F65: =F61-F66 -> 4965.112 | G65: =G61-G66 -> 5324.0404 | H65: =H61-H66 -> 5708.9157 | I65: =I61-I66 -> 6121.6137 | J65: =J61-J66 -> 6564.1456 | ... Q65: =Q61-Q66 -> 0
A66: Debito residuo a fine anno (anno 0 = mutuo erogato) | B66: =Parametri!$C$101 -> 60311.691 | C66: =IF(C64=0,Parametri!$C$101,MAX(0,-FV(Parametri!$C$102/12,C64,-Parametri!$C$105,Parametri!$C$101))) -> 60311.691 | D66: =IF(D64=0,Parametri!$C$101,MAX(0,-FV(Parametri!$C$102/12,D64,-Parametri!$C$105,Parametri!$C$101))) -> 55993.474 | E66: =IF(E64=0,Parametri!$C$101,MAX(0,-FV(Parametri!$C$102/12,E64,-Parametri!$C$105,Parametri!$C$101))) -> 51363.093 | F66: =IF(F64=0,Parametri!$C$101,MAX(0,-FV(Parametri!$C$102/12,F64,-Parametri!$C$105,Parametri!$C$101))) -> 46397.981 | G66: =IF(G64=0,Parametri!$C$101,MAX(0,-FV(Parametri!$C$102/12,G64,-Parametri!$C$105,Parametri!$C$101))) -> 41073.94 | H66: =IF(H64=0,Parametri!$C$101,MAX(0,-FV(Parametri!$C$102/12,H64,-Parametri!$C$105,Parametri!$C$101))) -> 35365.025 | I66: =IF(I64=0,Parametri!$C$101,MAX(0,-FV(Parametri!$C$102/12,I64,-Parametri!$C$105,Parametri!$C$101))) -> 29243.411 | J66: =IF(J64=0,Parametri!$C$101,MAX(0,-FV(Parametri!$C$102/12,J64,-Parametri!$C$105,Parametri!$C$101))) -> 22679.265 | ... Q66: =IF(Q64=0,Parametri!$C$101,MAX(0,-FV(Parametri!$C$102/12,Q64,-Parametri!$C$105,Parametri!$C$101))) -> 0
A67: Interessi pagati | C67: =C63*Parametri!$C$101*Parametri!$C$102/12+Parametri!$C$105*(C64-B64)-C65 -> 4221.8184 | D67: =D63*Parametri!$C$101*Parametri!$C$102/12+Parametri!$C$105*(D64-C64)-D65 -> 4085.0214 | E67: =E63*Parametri!$C$101*Parametri!$C$102/12+Parametri!$C$105*(E64-D64)-E65 -> 3772.8571 | F67: =F63*Parametri!$C$101*Parametri!$C$102/12+Parametri!$C$105*(F64-E64)-F65 -> 3438.1265 | G67: =G63*Parametri!$C$101*Parametri!$C$102/12+Parametri!$C$105*(G64-F64)-G65 -> 3079.1981 | H67: =H63*Parametri!$C$101*Parametri!$C$102/12+Parametri!$C$105*(H64-G64)-H65 -> 2694.3228 | I67: =I63*Parametri!$C$101*Parametri!$C$102/12+Parametri!$C$105*(I64-H64)-I65 -> 2281.6248 | J67: =J63*Parametri!$C$101*Parametri!$C$102/12+Parametri!$C$105*(J64-I64)-J65 -> 1839.0929 | ... Q67: =Q63*Parametri!$C$101*Parametri!$C$102/12+Parametri!$C$105*(Q64-P64)-Q65 -> 0
A68: Rata pagata nell'anno (capitale + interessi) | C68: =C65+C67 -> 4221.8184 | D68: =D65+D67 -> 8403.2385 | E68: =E65+E67 -> 8403.2385 | F68: =F65+F67 -> 8403.2385 | G68: =G65+G67 -> 8403.2385 | H68: =H65+H67 -> 8403.2385 | I68: =I65+I67 -> 8403.2385 | J68: =J65+J67 -> 8403.2385 | ... Q68: =Q65+Q67 -> 0
A69: Imposte con mutuo (gli interessi riducono solo l'IRES) | C69: =IF(Parametri!$C$64=1,C46,MAX(0,C45-C67)*Parametri!$C$68+MAX(0,C45)*Parametri!$C$69) -> 0 | D69: =IF(Parametri!$C$64=1,D46,MAX(0,D45-D67)*Parametri!$C$68+MAX(0,D45)*Parametri!$C$69) -> 0 | E69: =IF(Parametri!$C$64=1,E46,MAX(0,E45-E67)*Parametri!$C$68+MAX(0,E45)*Parametri!$C$69) -> 120.56482 | F69: =IF(Parametri!$C$64=1,F46,MAX(0,F45-F67)*Parametri!$C$68+MAX(0,F45)*Parametri!$C$69) -> 742.61297 | G69: =IF(Parametri!$C$64=1,G46,MAX(0,G45-G67)*Parametri!$C$68+MAX(0,G45)*Parametri!$C$69) -> 828.75577 | H69: =IF(Parametri!$C$64=1,H46,MAX(0,H45-H67)*Parametri!$C$68+MAX(0,H45)*Parametri!$C$69) -> 921.12585 | I69: =IF(Parametri!$C$64=1,I46,MAX(0,I45-I67)*Parametri!$C$68+MAX(0,I45)*Parametri!$C$69) -> 1127.5884 | J69: =IF(Parametri!$C$64=1,J46,MAX(0,J45-J67)*Parametri!$C$68+MAX(0,J45)*Parametri!$C$69) -> 1233.796 | ... Q69: =IF(Parametri!$C$64=1,Q46,MAX(0,Q45-Q67)*Parametri!$C$68+MAX(0,Q45)*Parametri!$C$69) -> 3104.367
A70: Utile netto con mutuo | C70: =C45-C67-C69 -> -8713.8654 | D70: =D45-D67-D69 -> -4364.0391 | E70: =E45-E67-E69 -> -802.01618 | F70: =F45-F67-F69 -> 1438.4839 | G70: =G45-G67-G69 -> 1711.2695 | H70: =H45-H67-H69 -> 2003.7747 | I70: =I45-I67-I69 -> 2595.0102 | J70: =J45-J67-J69 -> 2931.3345 | ... Q70: =Q45-Q67-Q69 -> 8022.3964
A71: Flusso di cassa dopo le rate (utile netto + ammortamenti − capitale rimborsato) | C71: =C70+C44-C65 -> -3206.3254 | D71: =D70+D44-D65 -> -3174.7162 | E71: =E70+E44-E65 -> 75.142451 | F71: =F70+F44-F65 -> 1980.9119 | G71: =G70+G44-G65 -> 1894.7691 | H71: =H70+H44-H65 -> 1802.399 | I71: =I70+I44-I65 -> 1595.9365 | J71: =J70+J44-J65 -> 1489.7289 | ... Q71: =Q70+Q44-Q65 -> 8022.3964
A72: Copertura del debito: (EBITDA − imposte) ÷ rata | C72: =IF(C68>0,(C43-C69)/C68,"") -> 0.24053449 | D72: =IF(D68>0,(D43-D69)/D68,"") -> 0.62220325 | E72: =IF(E68>0,(E43-E69)/E68,"") -> 1.0089421 | F72: =IF(F68>0,(F43-F69)/F68,"") -> 1.235732 | G72: =IF(G68>0,(G43-G69)/G68,"") -> 1.2254808 | H72: =IF(H68>0,(H43-H69)/H68,"") -> 1.2144886 | I72: =IF(I68>0,(I43-I69)/I68,"") -> 1.1899192 | J72: =IF(J68>0,(J43-J69)/J68,"") -> 1.1772803 | ... Q72: =IF(Q68>0,(Q43-Q69)/Q68,"")
A73: Flusso di cassa dei soci (anno 0 = capitale proprio versato) | B73: =-('Impianto e costi'!$G$73-Parametri!$C$101) -> 0 | C73: =C71 -> -3206.3254 | D73: =D71 -> -3174.7162 | E73: =E71 -> 75.142451 | F73: =F71 -> 1980.9119 | G73: =G71 -> 1894.7691 | H73: =H71 -> 1802.399 | I73: =I71 -> 1595.9365 | J73: =J71 -> 1489.7289 | ... Q73: =Q71 -> 8022.3964
A74: Flusso cumulato dei soci | B74: =B73 -> 0 | C74: =B74+C73 -> -3206.3254 | D74: =C74+D73 -> -6381.0416 | E74: =D74+E73 -> -6305.8992 | F74: =E74+F73 -> -4324.9873 | G74: =F74+G73 -> -2430.2182 | H74: =G74+H73 -> -627.81912 | I74: =H74+I73 -> 968.1174 | J74: =I74+J73 -> 2457.8463 | ... Q74: =P74+Q73 -> 36870.591
A75: Calcolo del punto di rientro (supporto) | C75: =IF(AND(B74<0,C74>=0),0+(-B74)/C73,"") | D75: =IF(AND(C74<0,D74>=0),1+(-C74)/D73,"") | E75: =IF(AND(D74<0,E74>=0),2+(-D74)/E73,"") | F75: =IF(AND(E74<0,F74>=0),3+(-E74)/F73,"") | G75: =IF(AND(F74<0,G74>=0),4+(-F74)/G73,"") | H75: =IF(AND(G74<0,H74>=0),5+(-G74)/H73,"") | I75: =IF(AND(H74<0,I74>=0),6+(-H74)/I73,"") -> 6.393386 | J75: =IF(AND(I74<0,J74>=0),7+(-I74)/J73,"") | K75: =IF(AND(J74<0,K74>=0),8+(-J74)/K73,"") | L75: =IF(AND(K74<0,L74>=0),9+(-K74)/L73,"") | M75: =IF(AND(L74<0,M74>=0),10+(-L74)/M73,"") | N75: =IF(AND(M74<0,N74>=0),11+(-M74)/N73,"") | O75: =IF(AND(N74<0,O74>=0),12+(-N74)/O73,"") | P75: =IF(AND(O74<0,P74>=0),13+(-O74)/P73,"") | Q75: =IF(AND(P74<0,Q74>=0),14+(-P74)/Q73,"")
A76: Payback dei soci: anni per recuperare capitale proprio e versamenti (anni) | B76: =IF(COUNT(C75:Q75)=0,IF(MIN(B74:Q74)>=0,"nessun capitale a rischio","oltre 15 anni: non rientra"),MIN(C75:Q75)) -> 6.393386
A77: Esborso massimo cumulato dei soci (picco, anni 0–15) | B77: =MAX(0,-MIN(B74:Q74)) -> 6381.0416
A78: Interessi totali pagati sul mutuo (15 anni) | B78: =SUM(C67:Q67) -> 27942.512
A79: Le rate sono mensili; il modello è annuale. Gli interessi riducono solo l'IRES (non l'IRAP, calcolata sull'EBIT); con regime forfettario non sono deducibili. Le perdite fiscali degli anni iniziali non vengono riportate agli anni successivi (semplificazione già presente nel modello). Flussi negativi = i soci devono versare cassa. Righe 43–56 = stessa attività senza mutuo.

Sheet Break-even
A1: Punto di pareggio e volume necessario
A2: Quanti litri bisogna vendere per coprire i costi fissi e per recuperare l'investimento in 5 anni (senza rate né interessi del mutuo).
A4: Voce | B4: Unità | C4: K220 | D4: Come si calcola
A5: Ricavo medio per litro venduto | B5: €/L | C5: =Parametri!$C$26*Parametri!$C$36+Parametri!$C$27*Parametri!$C$37/Parametri!$C$38 -> 4.4148641 | D5: Quota fusti × prezzo/L + quota bottiglie × prezzo/bottiglia ÷ 0,33
A6: Costo produzione per litro venduto (materie prime, detergenti, energia, acqua) | B6: €/L | C6: =((Parametri!$C$45+Parametri!$C$46)/100+Parametri!$C$48*Parametri!$C$49/100+Parametri!$C$50*Parametri!$C$51/100)/(1-Parametri!$C$28) -> 0.715625 | D6: Si divide per (1 − perdite) perché si produce più di quanto si vende
A7: Imballaggi bottiglie e consumabili fusti per litro venduto | B7: €/L | C7: =Parametri!$C$27/Parametri!$C$38*(Parametri!$C$52+Parametri!$C$53+Parametri!$C$54+Parametri!$C$55+Parametri!$C$56)+Parametri!$C$26*Parametri!$C$57/100 -> 0.22834165
A8: Accisa per litro venduto | B8: €/L | C8: =Parametri!$C$47*Parametri!$C$62*(1-Parametri!$C$63)/100 -> 0.244956 | D8: °P × aliquota × (1 − riduzione) ÷ 100
A9: Logistica per litro venduto | B9: €/L | C9: =C5*Parametri!$C$58 -> 0.1103716
A10: Margine di contribuzione per litro venduto | B10: €/L | C10: =C5-C6-C7-C8-C9 -> 3.1155699 | D10: Ricavo − costi variabili per litro
A11: Costi fissi annui a regime | B11: €/anno | C11: ='Business plan'!G42 -> 5725.354 | D11: Dal business plan (anno 5). L'INPS cresce con il reddito, quindi è solo approssimata
A12: Litri da vendere per il pareggio operativo | B12: L/anno | C12: =IF(C10<=0,"mai",C11/C10) -> 1837.6587 | D12: Costi fissi ÷ margine per litro (ante imposte e ammortamenti)
A13: Litri vendibili al massimo (capacità dopo perdite) | B13: L/anno | C13: =Parametri!$C$16*(1-Parametri!$C$28) -> 7948.8 | D13: Capacità × (1 − perdite)
A14: Il pareggio richiede questa quota della capacità | B14: % | C14: =IF(ISNUMBER(C12),C12/C13,"n/d") -> 0.23118693 | D14: Oltre 100% = serve più capacità (più tank o cotte più grandi)
A15: Esito | C15: =IF(ISNUMBER(C14),IF(C14<=1,"Pareggio entro la capacità","Pareggio OLTRE la capacità"),"Non raggiungibile") -> Pareggio entro la capacità
A16: Litri da vendere per rientrare in 5 anni (fissi + investimento ÷ 5) | B16: L/anno | C16: =IF(C10<=0,"mai",(C11+'Impianto e costi'!$G$73/5)/C10) -> 5709.2901 | D16: Approssimazione ante imposte, senza mutuo
A17: …in percentuale della capacità vendibile | B17: % | C17: =IF(ISNUMBER(C16),C16/C13,"n/d") -> 0.71825812
A18: Pareggio operativo se non paghi l'affitto | B18: L/anno | C18: =IF(C10<=0,"mai",(C11-Parametri!$C$73*12)/C10) -> 1837.6587 | D18: Caso di locale di proprietà
A19: Volume venduto previsto a regime (domanda indicata) | B19: L/anno | C19: =Parametri!$C$25 -> 5409 | D19: Fusti + bottiglie all'anno (Parametri), in litri
A20: Il pareggio richiede questa quota del volume previsto | B20: % | C20: =IF(ISNUMBER(C12),C12/C19,"n/d") -> 0.33974093 | D20: Oltre 100% = con la domanda indicata i costi fissi non sono coperti

Sheet Clienti potenziali
A1: Clienti potenziali in zona
A2: Locali trovati con Google Maps nel raggio di circa 30 km da Varallo (elenco non completo: mancano i locali non presenti su Maps, sagre, Pro Loco, associazioni e feste private). Non sappiamo quali abbiano già birra artigianale o contratti con distributori: il primo passo è telefonare. Km in linea d'aria da Varallo (su strada sono di più). Le celle blu sono ipotesi o campi da compilare.
A3: Riepilogo
B4: Locali nell'elenco (esclusi quelli marcati "Escl.") | C4: =COUNTA(B24:B72)-COUNTIF(J24:J72,"Escl.") -> 46 | D4: La quota coperta dipende dalle ipotesi blu qui sotto: sono stime mie, non dati misurati.
B5: di cui priorità A / B / C | C5: =COUNTIF(J24:J72,"A")&" / "&COUNTIF(J24:J72,"B")&" / "&COUNTIF(J24:J72,"C") -> 20 / 24 / 2
B6: Fusti/mese se tutti diventassero clienti | C6: =SUM(K24:K72) -> 29.2
B7: Fusti/mese attesi (con le probabilità di conquista) | C7: =SUM(M24:M72) -> 5.174
B8: Fusti/mese a regime nel modello (Parametri) | C8: =Parametri!C22 -> 12
B9: Quota del modello coperta dai clienti attesi | C9: =IF(C8=0,0,C7/C8) -> 0.43116667
B10: Locali da convertire per raggiungere il volume del modello (a media consumo) | C10: =IF(AVERAGEIF(J24:J72,"<>Escl.",K24:K72)=0,0,ROUNDUP(C8/AVERAGEIF(J24:J72,"<>Escl.",K24:K72),0)) -> 19
A11: Ipotesi di consumo e di conquista (stime mie, modificabili)
B12: Categoria | C12: Fusti/mese se cliente | D12: Nota | K12: Priorità | L12: Probabilità di conquista | M12: Criterio
B13: Pub / birreria | C13: 1.5 | D13: Un pub con una spina dedicata a voi consuma circa 1–2 fusti da 30 L al mese | K13: A | L13: 0.25 | M13: Entro circa 12 km (Varallo e Borgosesia): pub, bar, ristoranti, rivendite
B14: Bar / enoteca-bar | C14: 0.5 | D14: Bar: poche spine, rotazione lenta | K14: B | L14: 0.12 | M14: Tra 12 e 26 km, oppure agriturismi, rifugi e catering vicini
B15: Rivendita / enoteca | C15: 0.3 | D15: Soprattutto bottiglie: qui il valore è in fusti-equivalenti | K15: C | L15: 0.04 | M15: Oltre 26 km o poco adatti
B16: Ristorante / osteria / pizzeria | C16: 0.6 | D16: Una birra alla spina o poche bottiglie nel menu | K16: Escl. | L16: 0 | M16: Escluso (troppo lontano o non pertinente)
B17: Agriturismo / B&B / azienda agricola | C17: 0.4 | D17: Consumo stagionale, eventi e gruppi
B18: Hotel / rifugio di montagna | C18: 0.5 | D18: Stagionale e logistica difficile
B19: Catering / eventi / location | C19: 0.5 | D19: Fusti per matrimoni e feste: dipende dagli eventi
A22: Elenco clienti potenziali (ordinati per distanza da Varallo)
A23: N. | B23: Locale | C23: Categoria | D23: Comune | E23: Indirizzo | F23: Telefono | G23: Km da Varallo | H23: Google ★ | I23: Recensioni | J23: Priorità | K23: Fusti/mese se cliente | L23: Probabilità | M23: Fusti/mese attesi | N23: Stato contatto | O23: Nota | P23: Esito della telefonata | Q23: Mappa
A24: 1 | B24: WOOD Cafe' | C24: Bar / enoteca-bar | D24: Varallo (VC) | E24: Piazza S. Carlo Borromeo, 9 | F24: +39 348 899 0501 | G24: 0.2 | H24: 4.4 | I24: 131 | J24: A | K24: =IF(J24="Escl.",0,VLOOKUP(C24,$B$13:$C$19,2,FALSE())) -> 0.5 | L24: =VLOOKUP(J24,$K$13:$L$16,2,FALSE()) -> 0.25 | M24: =K24*L24 -> 0.125 | N24: Da contattare | Q24: Apri
A25: 2 | B25: Wine | C25: Bar / enoteca-bar | D25: Varallo (VC) | E25: Via Umberto 1° | G25: 0.2 | H25: 4.5 | I25: 19 | J25: A | K25: =IF(J25="Escl.",0,VLOOKUP(C25,$B$13:$C$19,2,FALSE())) -> 0.5 | L25: =VLOOKUP(J25,$K$13:$L$16,2,FALSE()) -> 0.25 | M25: =K25*L25 -> 0.125 | N25: Da contattare | Q25: Apri
A26: 3 | B26: Gambrinus Pub | C26: Pub / birreria | D26: Varallo (VC) | E26: Piazza Racchetti, 4 | F26: +39 339 273 0587 | G26: 0.3 | H26: 4.5 | I26: 411 | J26: A | K26: =IF(J26="Escl.",0,VLOOKUP(C26,$B$13:$C$19,2,FALSE())) -> 1.5 | L26: =VLOOKUP(J26,$K$13:$L$16,2,FALSE()) -> 0.25 | M26: =K26*L26 -> 0.375 | N26: Da contattare | Q26: Apri
A27: 4 | B27: La Miacceria Laboratorio Artigianale | C27: Bar / enoteca-bar | D27: Varallo (VC) | E27: Piazza Giovanni Calderini, 1 | F27: +39 377 311 7656 | G27: 0.3 | H27: 4.8 | I27: 104 | J27: A | K27: =IF(J27="Escl.",0,VLOOKUP(C27,$B$13:$C$19,2,FALSE())) -> 0.5 | L27: =VLOOKUP(J27,$K$13:$L$16,2,FALSE()) -> 0.25 | M27: =K27*L27 -> 0.125 | N27: Da contattare | Q27: Apri
A28: 5 | B28: Enoteca di Varallo | C28: Rivendita / enoteca | D28: Varallo (VC) | E28: Corso Roma, 14 | F28: +39 371 179 3295 | G28: 0.3 | H28: 4.6 | I28: 11 | J28: A | K28: =IF(J28="Escl.",0,VLOOKUP(C28,$B$13:$C$19,2,FALSE())) -> 0.3 | L28: =VLOOKUP(J28,$K$13:$L$16,2,FALSE()) -> 0.25 | M28: =K28*L28 -> 0.075 | N28: Da contattare | Q28: Apri
A29: 6 | B29: Il Cortiletto Pub Cafè | C29: Pub / birreria | D29: Varallo (VC) | E29: Corso Roma, 49 | F29: +39 331 211 7317 | G29: 0.4 | H29: 4.1 | I29: 387 | J29: A | K29: =IF(J29="Escl.",0,VLOOKUP(C29,$B$13:$C$19,2,FALSE())) -> 1.5 | L29: =VLOOKUP(J29,$K$13:$L$16,2,FALSE()) -> 0.25 | M29: =K29*L29 -> 0.375 | N29: Da contattare | Q29: Apri
A30: 7 | B30: Pane vino e poi... | C30: Rivendita / enoteca | D30: Varallo (VC) | E30: Corso Roma, 82 | F30: +39 345 717 5237 | G30: 0.4 | H30: 4.5 | I30: 15 | J30: A | K30: =IF(J30="Escl.",0,VLOOKUP(C30,$B$13:$C$19,2,FALSE())) -> 0.3 | L30: =VLOOKUP(J30,$K$13:$L$16,2,FALSE()) -> 0.25 | M30: =K30*L30 -> 0.075 | N30: Da contattare | Q30: Apri
A31: 8 | B31: La Locanda Dei Franceschi | C31: Ristorante / osteria / pizzeria | D31: Varallo (VC) | E31: Via D’Adda, 33e | F31: +39 344 509 8561 | G31: 0.7 | H31: 4.7 | I31: 20 | J31: A | K31: =IF(J31="Escl.",0,VLOOKUP(C31,$B$13:$C$19,2,FALSE())) -> 0.6 | L31: =VLOOKUP(J31,$K$13:$L$16,2,FALSE()) -> 0.25 | M31: =K31*L31 -> 0.15 | N31: Da contattare | Q31: Apri
A32: 9 | B32: Ristorante La Lum E Il Cassù | C32: Ristorante / osteria / pizzeria | D32: Varallo (VC) | E32: Via Principale, 4 | F32: +39 0163 52407 | G32: 0.7 | H32: 4.6 | I32: 276 | J32: A | K32: =IF(J32="Escl.",0,VLOOKUP(C32,$B$13:$C$19,2,FALSE())) -> 0.6 | L32: =VLOOKUP(J32,$K$13:$L$16,2,FALSE()) -> 0.25 | M32: =K32*L32 -> 0.15 | N32: Da contattare | Q32: Apri
A33: 10 | B33: Az.agr. Lavazzei di Defilippi Marco | C33: Agriturismo / B&B / azienda agricola | D33: Parone (VC) | E33: Località Sella 7 | F33: +39 349 775 1796 | G33: 3.2 | H33: 4.8 | I33: 156 | J33: B | K33: =IF(J33="Escl.",0,VLOOKUP(C33,$B$13:$C$19,2,FALSE())) -> 0.4 | L33: =VLOOKUP(J33,$K$13:$L$16,2,FALSE()) -> 0.12 | M33: =K33*L33 -> 0.048 | N33: Da contattare | Q33: Apri
A34: 11 | B34: Osteria DaMa | C34: Ristorante / osteria / pizzeria | D34: Varallo (VC) | E34: Località Solivo, 2 | F34: +39 340 147 8607 | G34: 3.4 | H34: 4.7 | I34: 131 | J34: A | K34: =IF(J34="Escl.",0,VLOOKUP(C34,$B$13:$C$19,2,FALSE())) -> 0.6 | L34: =VLOOKUP(J34,$K$13:$L$16,2,FALSE()) -> 0.25 | M34: =K34*L34 -> 0.15 | N34: Da contattare | Q34: Apri
A35: 12 | B35: Agriturismo Valdigoja | C35: Agriturismo / B&B / azienda agricola | D35: Parone (VC) | E35: Loc, Valdigoja | F35: +39 0163 54472 | G35: 3.5 | H35: 4.4 | I35: 173 | J35: B | K35: =IF(J35="Escl.",0,VLOOKUP(C35,$B$13:$C$19,2,FALSE())) -> 0.4 | L35: =VLOOKUP(J35,$K$13:$L$16,2,FALSE()) -> 0.12 | M35: =K35*L35 -> 0.048 | N35: Da contattare | Q35: Apri
A36: 13 | B36: B&B Land Wasser | C36: Agriturismo / B&B / azienda agricola | D36: Bocciolaro (VC) | F36: +39 348 045 2909 | G36: 4.3 | H36: 4.6 | I36: 58 | J36: B | K36: =IF(J36="Escl.",0,VLOOKUP(C36,$B$13:$C$19,2,FALSE())) -> 0.4 | L36: =VLOOKUP(J36,$K$13:$L$16,2,FALSE()) -> 0.12 | M36: =K36*L36 -> 0.048 | N36: Da contattare | Q36: Apri
A37: 14 | B37: Ristorante sosta camper Piano delle Fate | C37: Ristorante / osteria / pizzeria | D37: Cravagliana (VC) | F37: +39 0163 560829 | G37: 4.6 | H37: 4.4 | I37: 611 | J37: A | K37: =IF(J37="Escl.",0,VLOOKUP(C37,$B$13:$C$19,2,FALSE())) -> 0.6 | L37: =VLOOKUP(J37,$K$13:$L$16,2,FALSE()) -> 0.25 | M37: =K37*L37 -> 0.15 | N37: Da contattare | O37: Area sosta camper con bar-ristorante: afflusso turistico | Q37: Apri
A38: 15 | B38: Trattoria Il Giacomaccio | C38: Ristorante / osteria / pizzeria | D38: Boccioleto (VC) | E38: Via Roma, 37 | F38: +39 0163 75014 | G38: 11 | H38: 4.7 | I38: 1002 | J38: A | K38: =IF(J38="Escl.",0,VLOOKUP(C38,$B$13:$C$19,2,FALSE())) -> 0.6 | L38: =VLOOKUP(J38,$K$13:$L$16,2,FALSE()) -> 0.25 | M38: =K38*L38 -> 0.15 | N38: Da contattare | Q38: Apri
A39: 16 | B39: Osteria Del Moro Borgosesia | C39: Ristorante / osteria / pizzeria | D39: Borgosesia (VC) | E39: Piazza Parrocchiale, 4 | F39: +39 0163 22578 | G39: 11.2 | H39: 4.6 | I39: 335 | J39: A | K39: =IF(J39="Escl.",0,VLOOKUP(C39,$B$13:$C$19,2,FALSE())) -> 0.6 | L39: =VLOOKUP(J39,$K$13:$L$16,2,FALSE()) -> 0.25 | M39: =K39*L39 -> 0.15 | N39: Da contattare | Q39: Apri
A40: 17 | B40: Valsesia Wedding | C40: Catering / eventi / location | D40: Borgosesia (VC) | E40: Via Alberto Giordano, 59 | F40: +39 335 136 7777 | G40: 11.2 | H40: 5 | I40: 4 | J40: Escl. | K40: =IF(J40="Escl.",0,VLOOKUP(C40,$B$13:$C$19,2,FALSE())) -> 0 | L40: =VLOOKUP(J40,$K$13:$L$16,2,FALSE()) -> 0 | M40: =K40*L40 -> 0 | N40: Da contattare | O40: Servizio per matrimoni, non somministra: escluso | Q40: Apri
A41: 18 | B41: Nova Lounge Café Borgosesia | C41: Bar / enoteca-bar | D41: Borgosesia (VC) | E41: Piazza Martiri, 24 | F41: +39 393 218 2114 | G41: 11.3 | H41: 4.6 | I41: 25 | J41: A | K41: =IF(J41="Escl.",0,VLOOKUP(C41,$B$13:$C$19,2,FALSE())) -> 0.5 | L41: =VLOOKUP(J41,$K$13:$L$16,2,FALSE()) -> 0.25 | M41: =K41*L41 -> 0.125 | N41: Da contattare | Q41: Apri
A42: 19 | B42: Betty's Bier Eck | C42: Pub / birreria | D42: Borgosesia (VC) | E42: Via Frà Dolcino, 21 | F42: +39 347 121 0668 | G42: 11.4 | H42: 4.4 | I42: 502 | J42: A | K42: =IF(J42="Escl.",0,VLOOKUP(C42,$B$13:$C$19,2,FALSE())) -> 1.5 | L42: =VLOOKUP(J42,$K$13:$L$16,2,FALSE()) -> 0.25 | M42: =K42*L42 -> 0.375 | N42: Da contattare | Q42: Apri
A43: 20 | B43: gb club borgosesia | C43: Bar / enoteca-bar | D43: Borgosesia (VC) | E43: Piazza Giuseppe Mazzini, n°1 | F43: +39 0163 22269 | G43: 11.4 | H43: 4.4 | I43: 231 | J43: A | K43: =IF(J43="Escl.",0,VLOOKUP(C43,$B$13:$C$19,2,FALSE())) -> 0.5 | L43: =VLOOKUP(J43,$K$13:$L$16,2,FALSE()) -> 0.25 | M43: =K43*L43 -> 0.125 | N43: Da contattare | Q43: Apri
A44: 21 | B44: Bar GEM Wine and Spirits | C44: Bar / enoteca-bar | D44: Borgosesia (VC) | E44: Via XX Settembre, 15 | F44: +39 351 330 5845 | G44: 11.4 | H44: 4.8 | I44: 75 | J44: A | K44: =IF(J44="Escl.",0,VLOOKUP(C44,$B$13:$C$19,2,FALSE())) -> 0.5 | L44: =VLOOKUP(J44,$K$13:$L$16,2,FALSE()) -> 0.25 | M44: =K44*L44 -> 0.125 | N44: Da contattare | Q44: Apri
A45: 22 | B45: WonderBAR al parco | C45: Bar / enoteca-bar | D45: Borgosesia (VC) | E45: Via lins Fasani magni | F45: +39 333 247 5174 | G45: 11.7 | H45: 4.8 | I45: 66 | J45: A | K45: =IF(J45="Escl.",0,VLOOKUP(C45,$B$13:$C$19,2,FALSE())) -> 0.5 | L45: =VLOOKUP(J45,$K$13:$L$16,2,FALSE()) -> 0.25 | M45: =K45*L45 -> 0.125 | N45: Da contattare | Q45: Apri
A46: 23 | B46: La Verace Pizzeria gourmet e friggitoria | C46: Ristorante / osteria / pizzeria | D46: Borgosesia (VC) | E46: Corso Vercelli, 2 | F46: +39 0163 293122 | G46: 11.8 | H46: 4.6 | I46: 926 | J46: A | K46: =IF(J46="Escl.",0,VLOOKUP(C46,$B$13:$C$19,2,FALSE())) -> 0.6 | L46: =VLOOKUP(J46,$K$13:$L$16,2,FALSE()) -> 0.25 | M46: =K46*L46 -> 0.15 | N46: Da contattare | Q46: Apri
A47: 24 | B47: Blacksmith Borgosesia | C47: Ristorante / osteria / pizzeria | D47: Borgosesia (VC) | E47: Corso Vercelli, 123 | F47: +39 344 413 1635 | G47: 12 | H47: 4.6 | I47: 52 | J47: A | K47: =IF(J47="Escl.",0,VLOOKUP(C47,$B$13:$C$19,2,FALSE())) -> 0.6 | L47: =VLOOKUP(J47,$K$13:$L$16,2,FALSE()) -> 0.25 | M47: =K47*L47 -> 0.15 | N47: Da contattare | Q47: Apri
A48: 25 | B48: Agriturismo Al Mulin Dal Paja | C48: Agriturismo / B&B / azienda agricola | D48: Postua (VC) | E48: Via Molino, 1 | F48: +39 015 768799 | G48: 12.5 | H48: 4.6 | I48: 172 | J48: B | K48: =IF(J48="Escl.",0,VLOOKUP(C48,$B$13:$C$19,2,FALSE())) -> 0.4 | L48: =VLOOKUP(J48,$K$13:$L$16,2,FALSE()) -> 0.12 | M48: =K48*L48 -> 0.048 | N48: Da contattare | Q48: Apri
A49: 26 | B49: Agriturismo Il Bucaneve | C49: Agriturismo / B&B / azienda agricola | D49: Chioso (VC) | E49: Via Chioso, 18 | F49: +39 0163 71969 | G49: 12.5 | H49: 4.7 | I49: 13 | J49: B | K49: =IF(J49="Escl.",0,VLOOKUP(C49,$B$13:$C$19,2,FALSE())) -> 0.4 | L49: =VLOOKUP(J49,$K$13:$L$16,2,FALSE()) -> 0.12 | M49: =K49*L49 -> 0.048 | N49: Da contattare | Q49: Apri
A50: 27 | B50: StuzziCamy Catering&Events | C50: Catering / eventi / location | D50: Borgosesia (VC) | E50: Via Ottone Angelo, 1 | F50: +39 340 377 1389 | G50: 12.6 | H50: 4.8 | I50: 22 | J50: B | K50: =IF(J50="Escl.",0,VLOOKUP(C50,$B$13:$C$19,2,FALSE())) -> 0.5 | L50: =VLOOKUP(J50,$K$13:$L$16,2,FALSE()) -> 0.12 | M50: =K50*L50 -> 0.06 | N50: Da contattare | Q50: Apri
A51: 28 | B51: Mainente1988 Catering Matrimoni e Aziende | C51: Catering / eventi / location | D51: Borgosesia (VC) | E51: Via Ottone Angelo, 1 | F51: +39 340 984 5660 | G51: 12.6 | H51: 5 | I51: 3 | J51: B | K51: =IF(J51="Escl.",0,VLOOKUP(C51,$B$13:$C$19,2,FALSE())) -> 0.5 | L51: =VLOOKUP(J51,$K$13:$L$16,2,FALSE()) -> 0.12 | M51: =K51*L51 -> 0.06 | N51: Da contattare | Q51: Apri
A52: 29 | B52: Birba Caffe' di Gianello Monica | C52: Bar / enoteca-bar | D52: Serravalle Sesia (VC) | E52: Regione Naula, 27 | F52: +39 334 349 0173 | G52: 16.8 | H52: 4.5 | I52: 289 | J52: B | K52: =IF(J52="Escl.",0,VLOOKUP(C52,$B$13:$C$19,2,FALSE())) -> 0.5 | L52: =VLOOKUP(J52,$K$13:$L$16,2,FALSE()) -> 0.12 | M52: =K52*L52 -> 0.06 | N52: Da contattare | Q52: Apri
A53: 30 | B53: Ristorante Da Giovanni | C53: Ristorante / osteria / pizzeria | D53: Serravalle Sesia (VC) | E53: Via dei Ceri, 1 | F53: +39 0163 450157 | G53: 16.9 | H53: 4.5 | I53: 898 | J53: B | K53: =IF(J53="Escl.",0,VLOOKUP(C53,$B$13:$C$19,2,FALSE())) -> 0.6 | L53: =VLOOKUP(J53,$K$13:$L$16,2,FALSE()) -> 0.12 | M53: =K53*L53 -> 0.072 | N53: Da contattare | Q53: Apri
A54: 31 | B54: Azienda Agricola Le Beline s.s. - Baita del Noce | C54: Agriturismo / B&B / azienda agricola | D54: Grampa (VC) | F54: +39 349 644 0318 | G54: 17.3 | H54: 4.8 | I54: 22 | J54: C | K54: =IF(J54="Escl.",0,VLOOKUP(C54,$B$13:$C$19,2,FALSE())) -> 0.4 | L54: =VLOOKUP(J54,$K$13:$L$16,2,FALSE()) -> 0.04 | M54: =K54*L54 -> 0.016 | N54: Da contattare | O54: Azienda agricola/allevamento: probabilmente non somministra; da verificare | Q54: Apri
A55: 32 | B55: Azienda Agricola Floralp | C55: Agriturismo / B&B / azienda agricola | D55: Rusa (VC) | F55: +39 320 940 6211 | G55: 17.4 | H55: 4.7 | I55: 112 | J55: B | K55: =IF(J55="Escl.",0,VLOOKUP(C55,$B$13:$C$19,2,FALSE())) -> 0.4 | L55: =VLOOKUP(J55,$K$13:$L$16,2,FALSE()) -> 0.12 | M55: =K55*L55 -> 0.048 | N55: Da contattare | Q55: Apri
A56: 33 | B56: La Birreria di Grignasco (Giomar) | C56: Pub / birreria | D56: Grignasco (NO) | E56: Via Federico Peretti, 55 | F56: +39 0163 418434 | G56: 17.5 | H56: 4.1 | I56: 1082 | J56: B | K56: =IF(J56="Escl.",0,VLOOKUP(C56,$B$13:$C$19,2,FALSE())) -> 1.5 | L56: =VLOOKUP(J56,$K$13:$L$16,2,FALSE()) -> 0.12 | M56: =K56*L56 -> 0.18 | N56: Da contattare | O56: Ristorante-birreria molto frequentato; probabile contratto con grande distributore | Q56: Apri
A57: 34 | B57: Cascina dei Prapien | C57: Agriturismo / B&B / azienda agricola | D57: Mosso (BI) | E57: Regione Prapiano, 1 | F57: +39 339 776 6963 | G57: 19.7 | H57: 4.4 | I57: 185 | J57: B | K57: =IF(J57="Escl.",0,VLOOKUP(C57,$B$13:$C$19,2,FALSE())) -> 0.4 | L57: =VLOOKUP(J57,$K$13:$L$16,2,FALSE()) -> 0.12 | M57: =K57*L57 -> 0.048 | N57: Da contattare | Q57: Apri
A58: 35 | B58: Valsesia Vini | C58: Rivendita / enoteca | D58: Borgomanero (NO) | E58: Via Prevosto Felice Piana, 84/88 | F58: +39 0322 81681 | G58: 20.5 | H58: 4.7 | I58: 69 | J58: B | K58: =IF(J58="Escl.",0,VLOOKUP(C58,$B$13:$C$19,2,FALSE())) -> 0.3 | L58: =VLOOKUP(J58,$K$13:$L$16,2,FALSE()) -> 0.12 | M58: =K58*L58 -> 0.036 | N58: Da contattare | O58: Rivendita/distributore: possibile canale per le bottiglie | Q58: Apri
A59: 36 | B59: Agriturismo In Valle Sul Fiume | C59: Agriturismo / B&B / azienda agricola | D59: Calasca-Castiglione (VB) | E59: 3, Località Due Ponti, 28873 | F59: +39 347 873 1873 | G59: 21.2 | H59: 4.3 | I59: 324 | J59: B | K59: =IF(J59="Escl.",0,VLOOKUP(C59,$B$13:$C$19,2,FALSE())) -> 0.4 | L59: =VLOOKUP(J59,$K$13:$L$16,2,FALSE()) -> 0.12 | M59: =K59*L59 -> 0.048 | N59: Da contattare | Q59: Apri
A60: 37 | B60: Birreria Bèer Shop Melrose Place | C60: Rivendita / enoteca | D60: Romagnano Sesia (NO) | E60: Via Novara, 141 | F60: +39 348 734 4222 | G60: 23.3 | H60: 4.4 | I60: 173 | J60: B | K60: =IF(J60="Escl.",0,VLOOKUP(C60,$B$13:$C$19,2,FALSE())) -> 0.3 | L60: =VLOOKUP(J60,$K$13:$L$16,2,FALSE()) -> 0.12 | M60: =K60*L60 -> 0.036 | N60: Da contattare | O60: Beer shop: adatto soprattutto alle bottiglie (e come concorrente sugli scaffali) | Q60: Apri
A61: 38 | B61: Meteor Pub | C61: Pub / birreria | D61: Gattinara (VC) | E61: Corso Valsesia, 126 | G61: 23.8 | H61: 4.4 | I61: 378 | J61: B | K61: =IF(J61="Escl.",0,VLOOKUP(C61,$B$13:$C$19,2,FALSE())) -> 1.5 | L61: =VLOOKUP(J61,$K$13:$L$16,2,FALSE()) -> 0.12 | M61: =K61*L61 -> 0.18 | N61: Da contattare | Q61: Apri
A62: 39 | B62: Mulligans Irish Pub & Restaurant | C62: Pub / birreria | D62: Gattinara (VC) | E62: Corso Giuseppe Garibaldi, 165 | F62: +39 0163 823788 | G62: 24 | H62: 4.6 | I62: 1201 | J62: B | K62: =IF(J62="Escl.",0,VLOOKUP(C62,$B$13:$C$19,2,FALSE())) -> 1.5 | L62: =VLOOKUP(J62,$K$13:$L$16,2,FALSE()) -> 0.12 | M62: =K62*L62 -> 0.18 | N62: Da contattare | O62: Irish pub molto frequentato; probabile fornitura da marchi irlandesi/grandi birrifici | Q62: Apri
A63: 40 | B63: Birimbao Snc Di Paolo and Titian Barbaglia | C63: Pub / birreria | D63: Gattinara (VC) | E63: Corso Valsesia, 85 | F63: +39 0163 294178 | G63: 24 | H63: 4.5 | I63: 301 | J63: B | K63: =IF(J63="Escl.",0,VLOOKUP(C63,$B$13:$C$19,2,FALSE())) -> 1.5 | L63: =VLOOKUP(J63,$K$13:$L$16,2,FALSE()) -> 0.12 | M63: =K63*L63 -> 0.18 | N63: Da contattare | Q63: Apri
A64: 41 | B64: BrandOsteria | C64: Ristorante / osteria / pizzeria | D64: Gattinara (VC) | E64: Corso Valsesia, 1 | F64: +39 0163 417344 | G64: 24.2 | H64: 4.7 | I64: 247 | J64: B | K64: =IF(J64="Escl.",0,VLOOKUP(C64,$B$13:$C$19,2,FALSE())) -> 0.6 | L64: =VLOOKUP(J64,$K$13:$L$16,2,FALSE()) -> 0.12 | M64: =K64*L64 -> 0.072 | N64: Da contattare | Q64: Apri
A65: 42 | B65: Montagna di Luce Albergo Bar Ristorante | C65: Hotel / rifugio di montagna | D65: Alagna Valsesia (VC) | E65: Frazione Pedemonte, 19 | F65: +39 0163 922820 | G65: 25 | H65: 4.5 | I65: 627 | J65: B | K65: =IF(J65="Escl.",0,VLOOKUP(C65,$B$13:$C$19,2,FALSE())) -> 0.5 | L65: =VLOOKUP(J65,$K$13:$L$16,2,FALSE()) -> 0.12 | M65: =K65*L65 -> 0.06 | N65: Da contattare | O65: Hotel + bar + ristorante (stesso indirizzo di Ristorante Bar Montagna di Luce, contato una volta) | Q65: Apri
A66: 43 | B66: Rifugio Valle Vogna | C66: Hotel / rifugio di montagna | D66: Alagna Valsesia (VC) | E66: Frazione Sant’Antonio 1 | F66: +39 0163 326568 | G66: 25.2 | H66: 4.4 | I66: 502 | J66: B | K66: =IF(J66="Escl.",0,VLOOKUP(C66,$B$13:$C$19,2,FALSE())) -> 0.5 | L66: =VLOOKUP(J66,$K$13:$L$16,2,FALSE()) -> 0.12 | M66: =K66*L66 -> 0.06 | N66: Da contattare | O66: Alta valle: consegna da verificare, stagionale | Q66: Apri
A67: 44 | B67: Agriturismo Alagna | C67: Agriturismo / B&B / azienda agricola | D67: Alagna Valsesia (VC) | E67: Frazione Rusa | F67: +39 328 963 1049 | G67: 25.5 | H67: 4.4 | I67: 190 | J67: B | K67: =IF(J67="Escl.",0,VLOOKUP(C67,$B$13:$C$19,2,FALSE())) -> 0.4 | L67: =VLOOKUP(J67,$K$13:$L$16,2,FALSE()) -> 0.12 | M67: =K67*L67 -> 0.048 | N67: Da contattare | Q67: Apri
A68: 45 | B68: Refuge Tsar Senni | C68: Hotel / rifugio di montagna | D68: Follu | E68: Val d'Otro | F68: +39 0163 922952 | G68: 26.1 | H68: 4.6 | I68: 482 | J68: B | K68: =IF(J68="Escl.",0,VLOOKUP(C68,$B$13:$C$19,2,FALSE())) -> 0.5 | L68: =VLOOKUP(J68,$K$13:$L$16,2,FALSE()) -> 0.12 | M68: =K68*L68 -> 0.06 | N68: Da contattare | O68: Rifugio in quota (Val d'Otro): consegna fusti da verificare, stagionale | Q68: Apri
A69: 46 | B69: Rifugio Pastore | C69: Hotel / rifugio di montagna | D69: Alagna Valsesia (VC) | E69: Località Alpe Pile | F69: +39 0163 326570 | G69: 26.4 | H69: 4.6 | I69: 1554 | J69: B | K69: =IF(J69="Escl.",0,VLOOKUP(C69,$B$13:$C$19,2,FALSE())) -> 0.5 | L69: =VLOOKUP(J69,$K$13:$L$16,2,FALSE()) -> 0.12 | M69: =K69*L69 -> 0.06 | N69: Da contattare | O69: Rifugio in quota (Alpe Pile): consegna fusti da verificare, stagionale | Q69: Apri
A70: 47 | B70: Cascina Capitanio | C70: Catering / eventi / location | D70: Sillavengo (NO) | E70: Via S. Giuseppe, 21 | F70: +39 347 641 3452 | G70: 35.8 | H70: 4.7 | I70: 234 | J70: C | K70: =IF(J70="Escl.",0,VLOOKUP(C70,$B$13:$C$19,2,FALSE())) -> 0.5 | L70: =VLOOKUP(J70,$K$13:$L$16,2,FALSE()) -> 0.04 | M70: =K70*L70 -> 0.02 | N70: Da contattare | O70: Location per matrimoni: lontana, ma fusti per eventi privati | Q70: Apri
A71: 48 | B71: Il Giardino Incantato | C71: Catering / eventi / location | D71: Crova (VC) | E71: Via IV Novembre, 5 | F71: +39 351 471 6822 | G71: 54.4 | H71: 4.5 | I71: 62 | J71: Escl. | K71: =IF(J71="Escl.",0,VLOOKUP(C71,$B$13:$C$19,2,FALSE())) -> 0 | L71: =VLOOKUP(J71,$K$13:$L$16,2,FALSE()) -> 0 | M71: =K71*L71 -> 0 | N71: Da contattare | O71: Troppo lontano (oltre 50 km): escluso | Q71: Apri
A72: 49 | B72: Tenuta Ferraria - Location per Eventi | C72: Catering / eventi / location | D72: Casalrosso (VC) | E72: 45.297641, 8.358293 | F72: +39 327 435 7353 | G72: 58.3 | H72: 5 | I72: 2 | J72: Escl. | K72: =IF(J72="Escl.",0,VLOOKUP(C72,$B$13:$C$19,2,FALSE())) -> 0 | L72: =VLOOKUP(J72,$K$13:$L$16,2,FALSE()) -> 0 | M72: =K72*L72 -> 0 | N72: Da contattare | O72: Troppo lontano (oltre 50 km): escluso | Q72: Apri
A74: Altri birrifici e brewpub nelle vicinanze (concorrenti, non clienti)
A75: N. | B75: Locale | C75: Tipo | D75: Comune | E75: Indirizzo | F75: Telefono | G75: Km da Varallo | H75: Google ★ | I75: Recensioni | O75: Nota | Q75: Mappa
A76: 1 | B76: BAV - Birreria Artigiana Vallecellio | C76: Birrificio / brewpub | D76: Cellio (VC) | E76: Località Maddalena | F76: +39 331 588 4900 | G76: 9.2 | H76: 4.4 | I76: 34 | O76: Il più vicino (Cellio): birra di riso e di castagne, vendita sul territorio | Q76: Apri
A77: 2 | B77: In Beer Brewery | C77: Birrificio / brewpub | D77: Trivero (BI) | E77: Frazione Zoccolo, 3/B | F77: +39 377 154 1225 | G77: 17.7 | H77: 4.8 | I77: 66 | O77: Concorrente nella stessa area di vendita | Q77: Apri
A78: 3 | B78: Birrificio Z'AM STEG | C78: Birrificio / brewpub | D78: Mollia (VC) | E78: SP.299 Frazione Casacce | F78: +39 331 372 0086 | G78: 17.8 | H78: 4.6 | I78: 97 | O78: Brewpub sulla strada per Alagna (Mollia): intercetta il turismo della valle | Q78: Apri
A79: 4 | B79: Birrificio Artigianale Dr. Barbanera | C79: Birrificio / brewpub | D79: Cavallirio (NO) | E79: Via Giacomo Matteotti, 20 | F79: +39 0163 028007 | G79: 20.2 | H79: 4.8 | I79: 207 | O79: Concorrente nella stessa area di vendita | Q79: Apri
A80: 5 | B80: Birra Rèsga | C80: Birrificio / brewpub | D80: Prato Sesia (NO) | E80: Via Frà Dolcino, 44 | F80: +39 347 552 2927 | G80: 21.3 | H80: 4.8 | I80: 89 | O80: Concorrente nella stessa area di vendita | Q80: Apri
A81: 6 | B81: Birrificio la Tresca | C81: Birrificio / brewpub | D81: Baraggia (NO) | E81: Via Novara, 12 | F81: +39 0322 85248 | G81: 30.1 | H81: 4.8 | I81: 45 | O81: Concorrente nella stessa area di vendita | Q81: Apri
A82: 7 | B82: Birrificio Artigianale Viana | C82: Birrificio / brewpub | D82: Candelo (BI) | E82: Via Molignati, 12 | F82: +39 393 033 2728 | G82: 32.2 | H82: 5 | I82: 25 | O82: Concorrente nella stessa area di vendita | Q82: Apri
A83: 8 | B83: Hordeum - Birrificio Agricolo di Novara | C83: Birrificio / brewpub | D83: Novara (NO) | E83: Corso Vercelli, 120 | F83: +39 340 062 2835 | G83: 50 | H83: 4.6 | I83: 77 | O83: Fuori zona: solo come riferimento | Q83: Apri
A85: Fonte: Google Maps (ottobre 2026). Valutazioni e recensioni sono dati Google e cambiano nel tempo; telefoni e orari vanno verificati prima della chiamata. Non incluse sagre e feste patronali, Pro Loco e associazioni sportive: spesso sono i volumi più grandi per i fusti.

Sheet Cronoprogramma
A1: Cronoprogramma di avvio (12 mesi)
A2: Tempi indicativi: dipendono da Comune, ASL, ADM e dai tempi di consegna dei macchinari.
A4: Attività | B4: Responsabile | C4: M1 | D4: M2 | E4: M3 | F4: M4 | G4: M5 | H4: M6 | I4: M7 | J4: M8 | K4: M9 | L4: M10 | M4: M11 | N4: M12
A5: Analisi di mercato locale, assaggi e raccolta preordini | B5: Soci
A6: Verifica del locale di proprietà: destinazione d'uso, agibilità, sopralluogo (vedi Checklist locale) | B6: Socio architetto
A7: Business plan definitivo e scelta regime fiscale | B7: Soci/Commercialista
A8: Preventivo unico BrewTaurus (K220 + UT + chiller + CIP) e P&ID | B8: BrewTaurus
A9: Apertura P.IVA, Camera di Commercio, INPS | B9: Commercialista
A10: Adeguamento del locale (pavimenti, idraulica, elettrico, aspirazione) | B10: Imprese/Elettricista
A11: Ordine macchinari e consegna | B11: BrewTaurus
A12: Notifica sanitaria ASL + HACCP + sopralluogo | B12: ASL/Consulente
A13: Licenza ADM (deposito fiscale) e cauzione | B13: ADM
A14: Installazione, collaudo e cotte di prova | B14: Soci/Tecnico
A15: Etichette, marchio, sito, materiale commerciale | B15: Soci
A16: Prime vendite (fusti e bottiglie) e ramp-up | B16: Soci

Sheet Fonti
A1: Fonti consultate
A2: Le fonti sono state lette in ottobre 2026; verificare gli aggiornamenti prima di decidere.
A4: Argomento | B4: Fonte | C4: Link
A5: Prezzi macchinari BrewTaurus | B5: Sito BrewTaurus (K220, UT PRO, chiller, CIP kit, Hose Kit) | C5: Apri
A6: Unitank PRO (UT-200, PED, VAT) | B6: BrewTaurus PRO – Unitanks | C6: Apri
A7: Accisa 2026–2027 (2,98 €/hl/°P) | B7: Beverfood – Legge di Bilancio 2026 | C7: Apri
A8: Accisa ridotta microbirrifici (40%) | B8: La Casetta Craft Beer Crew | C8: Apri
A9: Accisa ridotta (50% secondo LdB 2025) | B9: Fisco di Prossimità | C9: Apri
A10: Definizione birra artigianale | B10: Confagricoltura | C10: Apri
A11: Iter autorizzativo | B11: La Casetta – Taproom: permessi | C11: Apri
A12: Iter e costi apertura microbirrificio | B12: Software Business Plan | C12: Apri
A13: Legislazione birra artigianale | B13: Birrartigianale.com | C13: Apri
A14: Mercato 2025 | B14: Cronache di Birra – Assobirra Annual Report 2025 | C14: Apri
A15: Prezzi e costi | B15: Il Mio Business Plan | C15: Apri
... A28: Esempio di prestito garantito dal Fondo PMI | B28: Banca Mediolanum – foglio informativo | C28: Apri

Sheet Checklist locale
A1: Checklist per il sopralluogo del locale
A2: Da compilare col socio architetto. Ogni punto indica a quale voce di costo del modello corrisponde: se il locale è già a posto, abbassa la quota dei lavori nei Parametri.
A4: Punto da verificare | B4: Perché conta | C4: Voce del modello (stima se manca) | D4: Esito (da compilare) | E4: Note
A5: Destinazione d'uso e agibilità | B5: La SCIA per attività produttiva alimentare richiede un locale idoneo e conforme (urbanistica, catasto, agibilità) | C5: Pratiche tecniche: già a 0 (se ne occupa il socio)
A6: Superficie utile e suddivisione in zone | B6: Servono zone separate: cottura, fermentazione, confezionamento, magazzino (40–80 m²) | C6: Layout da progettare
A7: Altezza utile e accessi | B7: Fermentatori e sala cottura devono entrare e stare sotto soffitto e impianti (vaso K220: 978 mm, 1.022 con coperchio). Porte e passaggi adeguati per le macchine | C7: Nessuna voce specifica
A8: Portata del solaio / pavimento | B8: Il sistema pieno pesa molto (un K40 pieno 120–160 kg; il K220 e i tank molto di più) | C8: Verifica strutturale se necessaria: non inclusa
A9: Pavimento lavabile con pendenza e pozzetto | B9: Requisito igienico-sanitario e per gli scarichi di lavaggio | C9: Pavimento con pendenze e pozzetti: 2.500 €
A10: Scarico e fognatura | B10: Smaltimento acque di lavaggio e di processo; sifone/pozzetto | C10: Impianto idraulico e scarichi: 2.500 € (non avete un idraulico)
A11: Acqua potabile (portata e pressione, acqua calda) | B11: Il consumo è circa 6 L di acqua per litro di birra, più i lavaggi | C11: Impianto idraulico e scarichi; trattamento acqua 300 € (filtri a carbone)
A12: Pareti e soffitti lavabili | B12: Requisito ASL | C12: Rivestimenti lavabili: 600 € (solo materiali: pareti e imbiancatura le fate voi)
A13: Corrente: potenza disponibile e monofase/trifase | B13: K220 2V circa 7 kW (da verificare), più chiller glicole e cella frigorifera: sommare le potenze con l'elettricista | C13: Allaccio elettrico/potenziamento 1.500–3.000 € + impianto interno 1.250–2.000 € (elettricista vostro)
A14: Estrazione dei vapori | B14: Il bollitore produce vapore: serve estrazione o condensatore (BrewTaurus vende condensatori ≈360 €) | C14: Ventilazione vapori: 300 € (finestra con ventola); con canna di estrazione 1.800 €
A15: Servizi igienici, antibagno e spogliatoio | B15: Spesso richiesti dall'ASL per stabilimenti alimentari: da verificare | C15: NON incluso nel modello
A16: Lavamani con comando non manuale | B16: Spesso richiesto in zona produzione: da verificare con ASL | C16: NON incluso nel modello
... A20: Vincoli del condominio, rumore e vicinato | B20: Orari, odori, regolamento condominiale e permessi comunali | C20: Nessuna voce
A23: Come usarla: dopo il sopralluogo, indica la quota dei lavori ancora necessari in Parametri (riga 'Quota dei lavori di adeguamento del locale necessari'). 100% = tutto da fare; 0% = locale già pronto.
